Workbook

Sheet pivot
A3: Sum of PURCHASER | C3: Column Labels
C4: 1 | D4: 2 | E4: 3 | F4: 4 | G4: 5 | H4: 6 | I4: 7 | J4: 8 | K4: 9 | L4: 10 | M4: 11 | N4: 12 | O4: 13 | P4: 14 | Q4: 15 | R4: 16 | S4: 17 | T4: 18 | U4: 19 | V4: 20 | W4: 21 | X4: 22 | Y4: 23 | Z4: 24 | AA4: 25 | AB4: 26 | AC4: 27 | AD4: 28 | AE4: 29 | AF4: 30 | AG4: 31 | AH4: 32 | AI4: 33 | AJ4: 34 | AK4: 35 | AL4: 36 | AM4: 37 | AN4: 38 | AO4: 39 | AP4: 40 | AQ4: 41 | AR4: 42 | AS4: 43 | AT4: 44 | AU4: 45 | AV4: 46 | AW4: 47 | AX4: 48 | AY4: 49 | AZ4: 50 | BA4: 51 | BB4: 52 | BC4: 53 | BD4: 54 | BE4: 55 | BF4: 56 | BG4: 57 | BH4: 58 | BI4: 190 | BJ4: 301 | BK4: 302 | BL4: 303 | BM4: 304 | BN4: 305 | BO4: 306 | BP4: 309 | BQ4: 310 | BR4: 401 | BS4: 402 | BT4: 403 | BU4: 404 | BV4: 409 | BW4: 501 | BX4: 502 | BY4: 503 | BZ4: 509 | CA4: 600 | CB4: 700 | CC4: Grand Total
A5: Row Labels | B5: Row label | C5: Paddy | D5: Maize | E5: Cassava | F5: Beans and Nuts | G5: Vegetables and Fruits | H5: Sugarcane | I5: Rubber (Latex) | J5: Other Crops | K5: Livestock | L5: Forestry | M5: Fishery | N5: Crude Oil and Coal | O5: Metal Ore | P5: Non-Metal Ore | Q5: Slaughtering | R5: Processing and Presering of Foods | S5: Rice and Other Grain Milling | T5: Sugar Refineries | U5: Other Foods | V5: Animal Food | W5: Beverages | X5: Tobacco Processing and Products | Y5: Spinning, Weaving and Bleaching | Z5: Textile Products | AA5: Paper and Paper Products | AB5: Printing and Publishing | AC5: Basic Chemical Products | AD5: Fertilizer and Pesticides | AE5: Other Chemical Products | AF5: Petroleum Refineries | AG5: Rubber Products | AH5: Plastic Wares | AI5: Cement and Concrete Products | AJ5: Other Non-metallic Products | AK5: Iron and Steel | AL5: Non-ferrous Metal | AM5: Fabricated Metal Products | AN5: Industrial Machinery | AO5: Electrical Machinery and Apparatus | AP5: Motor Vehicles and Repairing | AQ5: Other Transportation Equipment | AR5: Leather Products | AS5: Saw Mills and Wood Products | AT5: Other Manufacturing Products | AU5: Electricity and Gas | AV5: Water Works and Supply | AW5: Building Construction | AX5: Public Works and Other Construction | AY5: Trade | AZ5: Restaurants and Hotels | BA5: Transportation | BB5: Communication | BC5: Banking and Insurance | BD5: Real Estate | BE5: Business Services | BF5: Public Services | BG5: Other Services | BH5: Unclassified | BI5: Total Intermedite Transaction | BJ5: Private Consumption Expenditure | BK5: Government Consumption Expenditure | BL5: Gross Fixed Capital Formation | BM5: Increase in Stock | BN5: Exports (F.O.B.) | BO5: Special Exports | BP5: Total Final Demand | BQ5: Total Demand | BR5: Imports (C.I.F.) | BS5: Import Duty | BT5: Import Tax | BU5: Special Imports | BV5: Total Imports | BW5: Wholesale Trade Margin | BX5: Retail Trade Margin | BY5: Transportation Cost | BZ5: Total Margin and Transportation Cost | CA5: Control Total | CB5: Total Supply
A6: 1 | B6: Paddy | C6: 23826912 | D6: 0 | E6: 0 | F6: 0 | G6: 3226116 | H6: 0 | I6: 0 | J6: 13272 | K6: 9677525 | L6: 0 | M6: 0 | N6: 0 | O6: 0 | P6: 0 | Q6: 0 | R6: 29138 | S6: 300553587 | T6: 0 | U6: 0 | V6: 3103 | W6: 0 | X6: 0 | Y6: 0 | Z6: 0 | AA6: 187802 | AB6: 0 | AC6: 0 | AD6: 288979 | AE6: 0 | AF6: 0 | AG6: 0 | AH6: 0 | AI6: 0 | AJ6: 0 | AK6: 0 | AL6: 0 | AM6: 0 | AN6: 0 | AO6: 0 | AP6: 0 | AQ6: 0 | AR6: 0 | AS6: 0 | AT6: 68315 | AU6: 296681 | AV6: 0 | AW6: 0 | AX6: 0 | AY6: 0 | AZ6: 0 | BA6: 0 | BB6: 0 | BC6: 0 | BD6: 0 | BE6: 0 | BF6: 0 | BG6: 0 | BH6: 518802 | BI6: 338690232 | BJ6: 200503 | BK6: 26733 | BL6: 0 | BM6: -24818427 | BN6: 15619 | BO6: 0 | BP6: -24575572 | BQ6: 314114660 | BR6: -5 | BS6: 0 | BT6: 0 | BU6: 0 | BV6: -5 | BW6: -10756134 | BX6: -676903 | BY6: -1876161 | BZ6: -13309198 | CA6: 300805457 | CB6: 314114660 | CC6: 1530645691
A7: 2 | B7: Maize | C7: 0 | D7: 5865215 | E7: 0 | F7: 0 | G7: 0 | H7: 0 | I7: 0 | J7: 0 | K7: 4296645 | L7: 0 | M7: 0 | N7: 0 | O7: 0 | P7: 0 | Q7: 0 | R7: 781679 | S7: 861722 | T7: 0 | U7: 38007 | V7: 15692851 | W7: 0 | X7: 0 | Y7: 0 | Z7: 0 | AA7: 0 | AB7: 0 | AC7: 0 | AD7: 41504 | AE7: 0 | AF7: 0 | AG7: 0 | AH7: 0 | AI7: 0 | AJ7: 0 | AK7: 0 | AL7: 0 | AM7: 0 | AN7: 0 | AO7: 0 | AP7: 0 | AQ7: 0 | AR7: 0 | AS7: 0 | AT7: 0 | AU7: 43796 | AV7: 0 | AW7: 0 | AX7: 0 | AY7: 0 | AZ7: 619506 | BA7: 0 | BB7: 0 | BC7: 0 | BD7: 0 | BE7: 0 | BF7: 0 | BG7: 0 | BH7: 0 | BI7: 28240925 | BJ7: 566358 | BK7: 522790 | BL7: 0 | BM7: 27353408 | BN7: 3543545 | BO7: 0 | BP7: 31986101 | BQ7: 60227026 | BR7: -13906462 | BS7: -1124378 | BT7: -68 | BU7: 0 | BV7: -15030908 | BW7: -2251541 | BX7: -555919 | BY7: -480603 | BZ7: -3288063 | CA7: 41908055 | CB7: 60227026 | CC7: 246178217
A8: 3 | B8: Cassava | C8: 0 | D8: 0 | E8: 7591967 | F8: 3728 | G8: 0 | H8: 0 | I8: 0 | J8: 0 | K8: 12372 | L8: 0 | M8: 0 | N8: 0 | O8: 0 | P8: 0 | Q8: 0 | R8: 0 | S8: 53738757 | T8: 0 | U8: 817601 | V8: 609291 | W8: 0 | X8: 0 | Y8: 0 | Z8: 0 | AA8: 0 | AB8: 0 | AC8: 0 | AD8: 0 | AE8: 0 | AF8: 0 | AG8: 0 | AH8: 0 | AI8: 0 | AJ8: 0 | AK8: 0 | AL8: 0 | AM8: 0 | AN8: 0 | AO8: 0 | AP8: 0 | AQ8: 0 | AR8: 0 | AS8: 0 | AT8: 0 | AU8: 0 | AV8: 0 | AW8: 0 | AX8: 0 | AY8: 0 | AZ8: 596998 | BA8: 0 | BB8: 0 | BC8: 0 | BD8: 0 | BE8: 0 | BF8: 0 | BG8: 0 | BH8: 694544 | BI8: 64065258 | BJ8: 522579 | BK8: 380 | BL8: 0 | BM8: 12230209 | BN8: 0 | BO8: 0 | BP8: 12753168 | BQ8: 76818426 | BR8: 0 | BS8: 0 | BT8: 0 | BU8: 0 | BV8: 0 | BW8: -2122820 | BX8: -174398 | BY8: -520955 | BZ8: -2818173 | CA8: 74000253 | CB8: 76818426 | CC8: 375637611
A9: 4 | B9: Beans and Nuts | C9: 0 | D9: 0 | E9: 0 | F9: 654864 | G9: 3018992 | H9: 0 | I9: 0 | J9: 0 | K9: 2388736 | L9: 0 | M9: 0 | N9: 0 | O9: 0 | P9: 0 | Q9: 0 | R9: 12724250 | S9: 942118 | T9: 0 | U9: 12346452 | V9: 1388919 | W9: 5136281 | X9: 0 | Y9: 0 | Z9: 0 | AA9: 0 | AB9: 0 | AC9: 0 | AD9: 480022 | AE9: 0 | AF9: 0 | AG9: 0 | AH9: 0 | AI9: 0 | AJ9: 0 | AK9: 0 | AL9: 0 | AM9: 0 | AN9: 0 | AO9: 0 | AP9: 0 | AQ9: 0 | AR9: 0 | AS9: 0 | AT9: 0 | AU9: 0 | AV9: 0 | AW9: 0 | AX9: 0 | AY9: 0 | AZ9: 7520510 | BA9: 0 | BB9: 0 | BC9: 0 | BD9: 0 | BE9: 0 | BF9: 204294 | BG9: 0 | BH9: 609364 | BI9: 47414802 | BJ9: 1221069 | BK9: 109055 | BL9: 0 | BM9: -288257 | BN9: 2149301 | BO9: 0 | BP9: 3191168 | BQ9: 50605970 | BR9: -43130296 | BS9: -928667 | BT9: -15266 | BU9: 0 | BV9: -44074229 | BW9: -1122621 | BX9: -949787 | BY9: -76695 | BZ9: -2149103 | CA9: 4382638 | CB9: 50605970 | CC9: 114359854
A10: 5 | B10: Vegetables and Fruits | C10: 0 | D10: 0 | E10: 0 | F10: 0 | G10: 260340 | H10: 0 | I10: 0 | J10: 0 | K10: 2828602 | L10: 0 | M10: 0 | N10: 0 | O10: 0 | P10: 0 | Q10: 0 | R10: 60639500 | S10: 0 | T10: 0 | U10: 8583443 | V10: 534552 | W10: 7016675 | X10: 0 | Y10: 0 | Z10: 0 | AA10: 0 | AB10: 0 | AC10: 1104460 | AD10: 3988 | AE10: 1435019 | AF10: 0 | AG10: 0 | AH10: 0 | AI10: 0 | AJ10: 0 | AK10: 0 | AL10: 0 | AM10: 0 | AN10: 0 | AO10: 0 | AP10: 0 | AQ10: 0 | AR10: 0 | AS10: 0 | AT10: 0 | AU10: 0 | AV10: 0 | AW10: 0 | AX10: 0 | AY10: 0 | AZ10: 105084676 | BA10: 36428 | BB10: 0 | BC10: 0 | BD10: 0 | BE10: 0 | BF10: 22284008 | BG10: 2821187 | BH10: 1095279 | BI10: 213728157 | BJ10: 586918761 | BK10: 244132 | BL10: 0 | BM10: 0 | BN10: 165985221 | BO10: 2304919 | BP10: 755453033 | BQ10: 969181190 | BR10: -48485134 | BS10: -3764461 | BT10: -96691 | BU10: -1436930 | BV10: -53783216 | BW10: -114494467 | BX10: -139827431 | BY10: -15436605 | BZ10: -269758503 | CA10: 645639471 | CB10: 969181190 | CC10: 3875280793
A11: 6 | B11: Sugarcane | C11: 0 | D11: 0 | E11: 0 | F11: 0 | G11: 0 | H11: 4490083 | I11: 0 | J11: 0 | K11: 0 | L11: 0 | M11: 0 | N11: 0 | O11: 0 | P11: 0 | Q11: 0 | R11: 0 | S11: 0 | T11: 68681060 | U11: 0 | V11: 0 | W11: 206684 | X11: 0 | Y11: 0 | Z11: 0 | AA11: 0 | AB11: 0 | AC11: 0 | AD11: 2232 | AE11: 0 | AF11: 0 | AG11: 0 | AH11: 0 | AI11: 0 | AJ11: 0 | AK11: 0 | AL11: 0 | AM11: 0 | AN11: 0 | AO11: 0 | AP11: 0 | AQ11: 0 | AR11: 0 | AS11: 0 | AT11: 0 | AU11: 0 | AV11: 0 | AW11: 0 | AX11: 0 | AY11: 0 | AZ11: 0 | BA11: 0 | BB11: 0 | BC11: 0 | BD11: 0 | BE11: 0 | BF11: 0 | BG11: 0 | BH11: 10572 | BI11: 73390631 | BJ11: 7039 | BK11: 0 | BL11: 0 | BM11: 0 | BN11: 96 | BO11: 0 | BP11: 7135 | BQ11: 73397766 | BR11: -2 | BS11: 0 | BT11: 0 | BU11: 0 | BV11: -2 | BW11: -3338345 | BX11: -1849 | BY11: -2252169 | BZ11: -5592363 | CA11: 67805401 | CB11: 73397766 | CC11: 350211735
A12: 7 | B12: Rubber (Latex) | C12: 0 | D12: 0 | E12: 0 | F12: 0 | G12: 0 | H12: 0 | I12: 9953834 | J12: 0 | K12: 0 | L12: 0 | M12: 0 | N12: 0 | O12: 0 | P12: 0 | Q12: 0 | R12: 0 | S12: 0 | T12: 0 | U12: 0 | V12: 0 | W12: 0 | X12: 0 | Y12: 0 | Z12: 0 | AA12: 0 | AB12: 0 | AC12: 0 | AD12: 0 | AE12: 96766 | AF12: 0 | AG12: 105841640 | AH12: 0 | AI12: 0 | AJ12: 0 | AK12: 0 | AL12: 0 | AM12: 0 | AN12: 0 | AO12: 0 | AP12: 0 | AQ12: 15939 | AR12: 0 | AS12: 0 | AT12: 35200 | AU12: 0 | AV12: 0 | AW12: 0 | AX12: 0 | AY12: 0 | AZ12: 0 | BA12: 0 | BB12: 0 | BC12: 0 | BD12: 0 | BE12: 0 | BF12: 0 | BG12: 0 | BH12: 143396 | BI12: 116086775 | BJ12: 0 | BK12: 15785 | BL12: 0 | BM12: 67637322 | BN12: 52033737 | BO12: 0 | BP12: 119686844 | BQ12: 235773619 | BR12: -140664 | BS12: 0 | BT12: -8803 | BU12: 0 | BV12: -149467 | BW12: -13165354 | BX12: 0 | BY12: -1416395 | BZ12: -14581749 | CA12: 221042403 | CB12: 235773619 | CC12: 1134674447
A13: 8 | B13: Other Crops | C13: 16110576 | D13: 829269 | E13: 1504441 | F13: 357001 | G13: 50313291 | H13: 3021059 | I13: 2246407 | J13: 14706240 | K13: 848308 | L13: 334330 | M13: 440057 | N13: 0 | O13: 0 | P13: 0 | Q13: 0 | R13: 85851714 | S13: 13343855 | T13: 255049 | U13: 8856829 | V13: 255989 | W13: 28781423 | X13: 1479335 | Y13: 89683 | Z13: 12982 | AA13: 3128 | AB13: 0 | AC13: 0 | AD13: 163081 | AE13: 8090848 | AF13: 0 | AG13: 0 | AH13: 0 | AI13: 0 | AJ13: 0 | AK13: 0 | AL13: 0 | AM13: 0 | AN13: 0 | AO13: 0 | AP13: 0 | AQ13: 0 | AR13: 0 | AS13: 255123 | AT13: 160203 | AU13: 0 | AV13: 0 | AW13: 33565 | AX13: 1353797 | AY13: 0 | AZ13: 2046837 | BA13: 0 | BB13: 0 | BC13: 0 | BD13: 1997 | BE13: 402488 | BF13: 170045 | BG13: 1951087 | BH13: 476099 | BI13: 244746136 | BJ13: 3944695 | BK13: 2199489 | BL13: 0 | BM13: 203793 | BN13: 27642715 | BO13: 0 | BP13: 33990692 | BQ13: 278736828 | BR13: -51624855 | BS13: -1700242 | BT13: -444317 | BU13: -5001 | BV13: -53774415 | BW13: -14993310 | BX13: -8180463 | BY13: -3058595 | BZ13: -26232368 | CA13: 198730045 | CB13: 278736828 | CC13: 1153663791
A14: 9 | B14: Livestock | C14: 0 | D14: 0 | E14: 0 | F14: 0 | G14: 649482 | H14: 0 | I14: 0 | J14: 10772 | K14: 27489559 | L14: 0 | M14: 0 | N14: 0 | O14: 0 | P14: 0 | Q14: 300253373 | R14: 19003354 | S14: 0 | T14: 0 | U14: 4161915 | V14: 0 | W14: 0 | X14: 0 | Y14: 6667100 | Z14: 18311 | AA14: 0 | AB14: 0 | AC14: 0 | AD14: 284322 | AE14: 829987 | AF14: 0 | AG14: 0 | AH14: 0 | AI14: 0 | AJ14: 0 | AK14: 0 | AL14: 0 | AM14: 0 | AN14: 0 | AO14: 0 | AP14: 0 | AQ14: 0 | AR14: 1313067 | AS14: 0 | AT14: 25524 | AU14: 0 | AV14: 0 | AW14: 0 | AX14: 0 | AY14: 0 | AZ14: 7016546 | BA14: 0 | BB14: 0 | BC14: 0 | BD14: 0 | BE14: 0 | BF14: 1403526 | BG14: 36415 | BH14: 147330 | BI14: 369310583 | BJ14: 75750243 | BK14: 537858 | BL14: 3049362 | BM14: 0 | BN14: 15461511 | BO14: 0 | BP14: 94798974 | BQ14: 464109557 | BR14: -5602028 | BS14: -3501 | BT14: -128344 | BU14: 0 | BV14: -5733873 | BW14: -36985660 | BX14: -4414998 | BY14: -2394924 | BZ14: -43795582 | CA14: 414580102 | CB14: 464109557 | CC14: 2171959420
A15: 10 | B15: Forestry | C15: 4505 | D15: 0 | E15: 0 | F15: 0 | G15: 95611 | H15: 0 | I15: 0 | J15: 6674 | K15: 136453 | L15: 700494 | M15: 8062 | N15: 0 | O15: 0 | P15: 132475 | Q15: 0 | R15: 43408 | S15: 0 | T15: 15218 | U15: 845776 | V15: 23963 | W15: 33440 | X15: 5016 | Y15: 0 | Z15: 0 | AA15: 6063713 | AB15: 0 | AC15: 0 | AD15: 15938 | AE15: 1275852 | AF15: 0 | AG15: 110393 | AH15: 0 | AI15: 0 | AJ15: 127132 | AK15: 0 | AL15: 0 | AM15: 0 | AN15: 0 | AO15: 0 | AP15: 0 | AQ15: 7227 | AR15: 0 | AS15: 38887303 | AT15: 22766 | AU15: 345213 | AV15: 0 | AW15: 1147176 | AX15: 359353 | AY15: 0 | AZ15: 1066145 | BA15: 0 | BB15: 0 | BC15: 0 | BD15: 0 | BE15: 0 | BF15: 20510 | BG15: 0 | BH15: 336145 | BI15: 51835961 | BJ15: 10481989 | BK15: 0 | BL15: 0 | BM15: -38847602 | BN15: 9694480 | BO15: 0 | BP15: -18671133 | BQ15: 33164828 | BR15: -2716606 | BS15: -12523 | BT15: -202643 | BU15: 0 | BV15: -2931772 | BW15: -4021847 | BX15: -1697316 | BY15: -479105 | BZ15: -6198268 | CA15: 24034788 | CB15: 33164828 | CC15: 138434020
A16: 11 | B16: Fishery | C16: 0 | D16: 0 | E16: 0 | F16: 0 | G16: 0 | H16: 0 | I16: 0 | J16: 0 | K16: 4224945 | L16: 0 | M16: 11719193 | N16: 0 | O16: 0 | P16: 0 | Q16: 0 | R16: 82007018 | S16: 0 | T16: 0 | U16: 3173024 | V16: 2091654 | W16: 0 | X16: 0 | Y16: 0 | Z16: 0 | AA16: 0 | AB16: 0 | AC16: 0 | AD16: 0 | AE16: 4175208 | AF16: 0 | AG16: 0 | AH16: 0 | AI16: 0 | AJ16: 0 | AK16: 0 | AL16: 0 | AM16: 0 | AN16: 0 | AO16: 0 | AP16: 0 | AQ16: 0 | AR16: 0 | AS16: 0 | AT16: 0 | AU16: 0 | AV16: 0 | AW16: 0 | AX16: 0 | AY16: 0 | AZ16: 53290815 | BA16: 0 | BB16: 0 | BC16: 0 | BD16: 0 | BE16: 0 | BF16: 3605291 | BG16: 157531 | BH16: 238845 | BI16: 164683524 | BJ16: 107290773 | BK16: 141201 | BL16: 3154870 | BM16: 0 | BN16: 4047601 | BO16: 0 | BP16: 114634445 | BQ16: 279317969 | BR16: -11276066 | BS16: -108065 | BT16: -19107 | BU16: 0 | BV16: -11403238 | BW16: -31308028 | BX16: -31178009 | BY16: -5422074 | BZ16: -67908111 | CA16: 200006620 | CB16: 279317969 | CC16: 1158655798
A17: 12 | B17: Crude Oil and Coal | C17: 0 | D17: 0 | E17: 0 | F17: 0 | G17: 0 | H17: 0 | I17: 0 | J17: 0 | K17: 0 | L17: 0 | M17: 0 | N17: 15879688 | O17: 0 | P17: 0 | Q17: 0 | R17: 0 | S17: 0 | T17: 0 | U17: 0 | V17: 0 | W17: 0 | X17: 0 | Y17: 0 | Z17: 0 | AA17: 0 | AB17: 0 | AC17: 3145740 | AD17: 0 | AE17: 7013921 | AF17: 807407767 | AG17: 0 | AH17: 0 | AI17: 7448520 | AJ17: 0 | AK17: 0 | AL17: 5289759 | AM17: 0 | AN17: 0 | AO17: 0 | AP17: 0 | AQ17: 0 | AR17: 0 | AS17: 0 | AT17: 0 | AU17: 401159406 | AV17: 0 | AW17: 0 | AX17: 0 | AY17: 0 | AZ17: 0 | BA17: 0 | BB17: 0 | BC17: 0 | BD17: 0 | BE17: 0 | BF17: 0 | BG17: 0 | BH17: 87013 | BI17: 1247431814 | BJ17: 0 | BK17: 0 | BL17: 0 | BM17: 119611124 | BN17: 15399283 | BO17: 0 | BP17: 135010407 | BQ17: 1382442221 | BR17: -935241246 | BS17: 0 | BT17: -79102992 | BU17: 0 | BV17: -1014344238 | BW17: -877229 | BX17: 0 | BY17: -819088 | BZ17: -1696317 | CA17: 366401666 | CB17: 1382442221 | CC17: 3864089440
... A64: 190 | B64: Total Intermedite Transaction | C64: 106906674 | D64: 16923776 | E64: 26099879 | F64: 2062686 | G64: 239251631 | H64: 28326762 | I64: 50993258 | J64: 80466542 | K64: 224589912 | L64: 6037452 | M64: 101679877 | N64: 144695129 | O64: 101932 | P64: 54795133 | Q64: 345592022 | R64: 610662137 | S64: 425142761 | T64: 92812194 | U64: 214128989 | V64: 58891734 | W64: 292450233 | X64: 10592862 | Y64: 124948797 | Z64: 200384361 | AA64: 140145752 | AB64: 53246623 | AC64: 556724292 | AD64: 52473965 | AE64: 318116496 | AF64: 964139721 | AG64: 273556458 | AH64: 357430771 | AI64: 131262408 | AJ64: 190601782 | AK64: 199798869 | AL64: 82274692 | AM64: 334841045 | AN64: 402788746 | AO64: 2641849482 | AP64: 1568170254 | AQ64: 66076851 | AR64: 59496577 | AS64: 159521558 | AT64: 950128273 | AU64: 1054356045 | AV64: 24539836 | AW64: 473984576 | AX64: 471271482 | AY64: 885263498 | AZ64: 875765624 | BA64: 814403852 | BB64: 220025772 | BC64: 542128847 | BD64: 159728075 | BE64: 774493305 | BF64: 693426474 | BG64: 478251118 | BH64: 135398550 | BI64: 20564218402 | BJ64: 8786511895 | BK64: 2951397062 | BL64: 3803228016 | BM64: 859985000 | BN64: 8568939920 | BO64: 813739550 | BP64: 25783801443 | BQ64: 46348019845 | BR64: -8525584600 | BS64: -102067001 | BT64: -412509295 | BU64: -1006557745 | BV64: -10046718641 | BW64: 0 | BX64: 0 | BY64: 0 | BZ64: 0 | CA64: 36301301204 | CB64: 46348019845 | CC64: 201599943302
A65: 201 | B65: Wages and Salaries | C65: 66711643 | D65: 10628282 | E65: 18683997 | F65: 767311 | G65: 136013312 | H65: 18783938 | I65: 64784079 | J65: 35413750 | K65: 50686440 | L65: 6320044 | M65: 26891695 | N65: 42087971 | O65: 22061 | P65: 19573576 | Q65: 49425595 | R65: 39310178 | S65: 27530408 | T65: 16567714 | U65: 25110263 | V65: 3185990 | W65: 28569844 | X65: 2936191 | Y65: 17141312 | Z65: 29888490 | AA65: 16018297 | AB65: 8521990 | AC65: 86118488 | AD65: 5605242 | AE65: 46699106 | AF65: 19313941 | AG65: 23030390 | AH65: 47442202 | AI65: 21976498 | AJ65: 29329386 | AK65: 18482114 | AL65: 19138116 | AM65: 53518694 | AN65: 52341917 | AO65: 211962643 | AP65: 182634401 | AQ65: 14952073 | AR65: 9470241 | AS65: 36677620 | AT65: 102883422 | AU65: 124771661 | AV65: 12984883 | AW65: 41787909 | AX65: 92574143 | AY65: 647824586 | AZ65: 127021412 | BA65: 112659098 | BB65: 111491741 | BC65: 376967948 | BD65: 56449574 | BE65: 157051770 | BF65: 1568187883 | BG65: 195459789 | BH65: 34338703 | BI65: 5402721965 | CC65: 10805443930
A66: 202 | B66: Operating Surplus | C66: 103830453 | D66: 12857217 | E66: 26105667 | F66: 1495111 | G66: 236904462 | H66: 28074623 | I66: 97839571 | J66: 74033448 | K66: 118896569 | L66: 9645342 | M66: 50955088 | N66: 73605379 | O66: 46442 | P66: 40933335 | Q66: 101568841 | R66: 65093679 | S66: 42181828 | T66: 26116643 | U66: 41579323 | V66: 5546964 | W66: 55224412 | X66: 5869258 | Y66: 25551965 | Z66: 37597366 | AA66: 26432469 | AB66: 9746331 | AC66: 113625088 | AD66: 7866354 | AE66: 66058854 | AF66: 17259410 | AG66: 37332756 | AH66: 54828558 | AI66: 34399811 | AJ66: 34035645 | AK66: 26131144 | AL66: 24360395 | AM66: 83521995 | AN66: 70657723 | AO66: 320472134 | AP66: 207807404 | AQ66: 22816474 | AR66: 11479631 | AS66: 48466444 | AT66: 151097808 | AU66: 160731710 | AV66: 15125897 | AW66: 53817134 | AX66: 117461623 | AY66: 1316903123 | AZ66: 151103069 | BA66: 137626748 | BB66: 134587008 | BC66: 568994615 | BD66: 100405038 | BE66: 200100257 | BF66: 178554120 | BG66: 172036260 | BH66: 66417821 | BI66: 6023813837 | CC66: 12047627674
A67: 203 | B67: Depreciation | C67: 23207172 | D67: 1477950 | E67: 3073928 | F67: 55352 | G67: 33149151 | H67: 7826419 | I67: 7305765 | J67: 8717527 | K67: 19729403 | L67: 1414583 | M67: 20353707 | N67: 64631360 | O67: 13759 | P67: 10081721 | Q67: 26345577 | R67: 33751869 | S67: 18849197 | T67: 16007977 | U67: 16841816 | V67: 2177845 | W67: 29391696 | X67: 1342188 | Y67: 16210599 | Z67: 15295478 | AA67: 13748888 | AB67: 5121897 | AC67: 58052753 | AD67: 2782923 | AE67: 28547955 | AF67: 57550155 | AG67: 23223244 | AH67: 30645892 | AI67: 14237400 | AJ67: 21217832 | AK67: 9025763 | AL67: 7725868 | AM67: 24961642 | AN67: 33787543 | AO67: 153620165 | AP67: 108764737 | AQ67: 6793652 | AR67: 4893238 | AS67: 15956666 | AT67: 61092259 | AU67: 167999545 | AV67: 16099776 | AW67: 34180226 | AX67: 65629867 | AY67: 351052090 | AZ67: 99217482 | BA67: 117734997 | BB67: 105107866 | BC67: 135087385 | BD67: 316387538 | BE67: 73000455 | BF67: 394879485 | BG67: 74676300 | BH67: 30542477 | BI67: 3040598000 | CC67: 6081196000
A68: 204 | B68: Indirect Taxes less Subsidies | C68: 149515 | D68: 20830 | E68: 36782 | F68: 2178 | G68: 320915 | H68: -15206341 | I68: 119730 | J68: 98778 | K68: 677778 | L68: 617367 | M68: 126253 | N68: 41381827 | O68: 4753 | P68: 3236017 | Q68: 5776573 | R68: 22090987 | S68: 13128977 | T68: -1373182 | U68: 6513021 | V68: 1506350 | W68: 152310138 | X68: 29375406 | Y68: 3967570 | Z68: 8664710 | AA68: 4237165 | AB68: 1678479 | AC68: 20642223 | AD68: 1511548 | AE68: 13334411 | AF68: 204210841 | AG68: 8217988 | AH68: 10581774 | AI68: 4356519 | AJ68: 6449318 | AK68: 8315757 | AL68: 4924091 | AM68: 13275908 | AN68: 15140477 | AO68: 79347221 | AP68: 115825059 | AQ68: 2387607 | AR68: 2148117 | AS68: 5624269 | AT68: 28174403 | AU68: 32533488 | AV68: 2513142 | AW68: 8943455 | AX68: 11176160 | AY68: 85282953 | AZ68: 39525716 | BA68: 25199552 | BB68: 12593641 | BC68: 103782658 | BD68: 18624255 | BE68: 29403529 | BF68: 8993207 | BG68: 61751904 | BH68: 5695233 | BI68: 1269949000 | CC68: 2539898000
A69: 209 | B69: Total Value Added | C69: 193898783 | D69: 24984279 | E69: 47900374 | F69: 2319952 | G69: 406387840 | H69: 39478639 | I69: 170049145 | J69: 118263503 | K69: 189990190 | L69: 17997336 | M69: 98326743 | N69: 221706537 | O69: 87015 | P69: 73824649 | Q69: 183116586 | R69: 160246713 | S69: 101690410 | T69: 57319152 | U69: 90044423 | V69: 12417149 | W69: 265496090 | X69: 39523043 | Y69: 62871446 | Z69: 91446044 | AA69: 60436819 | AB69: 25068697 | AC69: 278438552 | AD69: 17766067 | AE69: 154640326 | AF69: 298334347 | AG69: 91804378 | AH69: 143498426 | AI69: 74970228 | AJ69: 91032181 | AK69: 61954778 | AL69: 56148470 | AM69: 175278239 | AN69: 171927660 | AO69: 765402163 | AP69: 615031601 | AQ69: 46949806 | AR69: 27991227 | AS69: 106724999 | AT69: 343247892 | AU69: 486036404 | AV69: 46723698 | AW69: 138728724 | AX69: 286841793 | AY69: 2401062752 | AZ69: 416867679 | BA69: 393220395 | BB69: 363780256 | BC69: 1184832606 | BD69: 491866405 | BE69: 459556011 | BF69: 2150614695 | BG69: 503924253 | BH69: 136994234 | BI69: 15737082802 | CC69: 31474165604
A70: 210 | B70: Control Total | C70: 300805457 | D70: 41908055 | E70: 74000253 | F70: 4382638 | G70: 645639471 | H70: 67805401 | I70: 221042403 | J70: 198730045 | K70: 414580102 | L70: 24034788 | M70: 200006620 | N70: 366401666 | O70: 188947 | P70: 128619782 | Q70: 528708608 | R70: 770908850 | S70: 526833171 | T70: 150131346 | U70: 304173412 | V70: 71308883 | W70: 557946323 | X70: 50115905 | Y70: 187820243 | Z70: 291830405 | AA70: 200582571 | AB70: 78315320 | AC70: 835162844 | AD70: 70240032 | AE70: 472756822 | AF70: 1262474068 | AG70: 365360836 | AH70: 500929197 | AI70: 206232636 | AJ70: 281633963 | AK70: 261753647 | AL70: 138423162 | AM70: 510119284 | AN70: 574716406 | AO70: 3407251645 | AP70: 2183201855 | AQ70: 113026657 | AR70: 87487804 | AS70: 266246557 | AT70: 1293376165 | AU70: 1540392449 | AV70: 71263534 | AW70: 612713300 | AX70: 758113275 | AY70: 3286326250 | AZ70: 1292633303 | BA70: 1207624247 | BB70: 583806028 | BC70: 1726961453 | BD70: 651594480 | BE70: 1234049316 | BF70: 2844041169 | BG70: 982175371 | BH70: 272392784 | BI70: 36301301204 | CC70: 72602602408
A71: Grand Total | C71: 902416371 | D71: 125724165 | E71: 222000759 | F71: 13147914 | G71: 1936918413 | H71: 203416203 | I71: 663127209 | J71: 596190135 | K71: 1243740306 | L71: 72104364 | M71: 600019860 | N71: 1099204998 | O71: 566841 | P71: 385859346 | Q71: 1586125824 | R71: 2312726550 | S71: 1580499513 | T71: 450394038 | U71: 912520236 | V71: 213926649 | W71: 1673838969 | X71: 150347715 | Y71: 563460729 | Z71: 875491215 | AA71: 601747713 | AB71: 234945960 | AC71: 2505488532 | AD71: 210720096 | AE71: 1418270466 | AF71: 3787422204 | AG71: 1096082508 | AH71: 1502787591 | AI71: 618697908 | AJ71: 844901889 | AK71: 785260941 | AL71: 415269486 | AM71: 1530357852 | AN71: 1724149218 | AO71: 10221754935 | AP71: 6549605565 | AQ71: 339079971 | AR71: 262463412 | AS71: 798739671 | AT71: 3880128495 | AU71: 4621177347 | AV71: 213790602 | AW71: 1838139900 | AX71: 2274339825 | AY71: 9858978750 | AZ71: 3877899909 | BA71: 3622872741 | BB71: 1751418084 | BC71: 5180884359 | BD71: 1954783440 | BE71: 3702147948 | BF71: 8532123507 | BG71: 2946526113 | BH71: 817178352 | BI71: 108903903612 | BJ71: 17573023790 | BK71: 5902794124 | BL71: 7606456032 | BM71: 1719970000 | BN71: 17137879840 | BO71: 1627479100 | BP71: 51567602886 | BQ71: 92696039690 | BR71: -17051169200 | BS71: -204134002 | BT71: -825018590 | BU71: -2013115490 | BV71: -20093437282 | BW71: 0 | BX71: 0 | BY71: 0 | BZ71: 0 | CA71: 72602602408 | CB71: 92696039690 | CC71: 538750820220

Sheet proc
C1: Paddy | D1: Maize | E1: Cassava | F1: Beans and Nuts | G1: Vegetables and Fruits | H1: Sugarcane | I1: Rubber (Latex) | J1: Other Crops | K1: Livestock | L1: Forestry | M1: Fishery | N1: Crude Oil and Coal | O1: Metal Ore | P1: Non-Metal Ore | Q1: Slaughtering | R1: Processing and Presering of Foods | S1: Rice and Other Grain Milling | T1: Sugar Refineries | U1: Other Foods | V1: Animal Food | W1: Beverages | X1: Tobacco Processing and Products | Y1: Spinning, Weaving and Bleaching | Z1: Textile Products | AA1: Paper and Paper Products | AB1: Printing and Publishing | AC1: Basic Chemical Products | AD1: Fertilizer and Pesticides | AE1: Other Chemical Products | AF1: Petroleum Refineries | AG1: Rubber Products | AH1: Plastic Wares | AI1: Cement and Concrete Products | AJ1: Other Non-metallic Products | AK1: Iron and Steel | AL1: Non-ferrous Metal | AM1: Fabricated Metal Products | AN1: Industrial Machinery | AO1: Electrical Machinery and Apparatus | AP1: Motor Vehicles and Repairing | AQ1: Other Transportation Equipment | AR1: Leather Products | AS1: Saw Mills and Wood Products | AT1: Other Manufacturing Products | AU1: Electricity and Gas | AV1: Water Works and Supply | AW1: Building Construction | AX1: Public Works and Other Construction | AY1: Trade | AZ1: Restaurants and Hotels | BA1: Transportation | BB1: Communication | BC1: Banking and Insurance | BD1: Real Estate | BE1: Business Services | BF1: Public Services | BG1: Other Services | BH1: Unclassified | BI1: Total Intermedite Transaction | BJ1: Private Consumption Expenditure | BK1: Government Consumption Expenditure | BL1: Gross Fixed Capital Formation | BM1: Increase in Stock | BN1: Exports (F.O.B.) | BO1: Special Exports | BP1: Total Final Demand | BQ1: Total Demand | BR1: Imports (C.I.F.) | BS1: Import Duty | BT1: Import Tax | BU1: Special Imports | BV1: Total Imports | BW1: Wholesale Trade Margin | BX1: Retail Trade Margin | BY1: Transportation Cost | BZ1: Total Margin and Transportation Cost | CA1: Control Total | CB1: Total Supply
A2: 1 | B2: Paddy | C2: 23826912 | D2: 0 | E2: 0 | F2: 0 | G2: 3226116 | H2: 0 | I2: 0 | J2: 13272 | K2: 9677525 | L2: 0 | M2: 0 | N2: 0 | O2: 0 | P2: 0 | Q2: 0 | R2: 29138 | S2: 300553587 | T2: 0 | U2: 0 | V2: 3103 | W2: 0 | X2: 0 | Y2: 0 | Z2: 0 | AA2: 187802 | AB2: 0 | AC2: 0 | AD2: 288979 | AE2: 0 | AF2: 0 | AG2: 0 | AH2: 0 | AI2: 0 | AJ2: 0 | AK2: 0 | AL2: 0 | AM2: 0 | AN2: 0 | AO2: 0 | AP2: 0 | AQ2: 0 | AR2: 0 | AS2: 0 | AT2: 68315 | AU2: 296681 | AV2: 0 | AW2: 0 | AX2: 0 | AY2: 0 | AZ2: 0 | BA2: 0 | BB2: 0 | BC2: 0 | BD2: 0 | BE2: 0 | BF2: 0 | BG2: 0 | BH2: 518802 | BI2: 338690232 | BJ2: 200503 | BK2: 26733 | BL2: 0 | BM2: -24818427 | BN2: 15619 | BO2: 0 | BP2: -24575572 | BQ2: 314114660 | BR2: -5 | BS2: 0 | BT2: 0 | BU2: 0 | BV2: -5 | BW2: -10756134 | BX2: -676903 | BY2: -1876161 | BZ2: -13309198 | CA2: 300805457 | CB2: 314114660 | CC2: =(BN2+BO2)/CB2*100 -> 0.0049723881
A3: 2 | B3: Maize | C3: 0 | D3: 5865215 | E3: 0 | F3: 0 | G3: 0 | H3: 0 | I3: 0 | J3: 0 | K3: 4296645 | L3: 0 | M3: 0 | N3: 0 | O3: 0 | P3: 0 | Q3: 0 | R3: 781679 | S3: 861722 | T3: 0 | U3: 38007 | V3: 15692851 | W3: 0 | X3: 0 | Y3: 0 | Z3: 0 | AA3: 0 | AB3: 0 | AC3: 0 | AD3: 41504 | AE3: 0 | AF3: 0 | AG3: 0 | AH3: 0 | AI3: 0 | AJ3: 0 | AK3: 0 | AL3: 0 | AM3: 0 | AN3: 0 | AO3: 0 | AP3: 0 | AQ3: 0 | AR3: 0 | AS3: 0 | AT3: 0 | AU3: 43796 | AV3: 0 | AW3: 0 | AX3: 0 | AY3: 0 | AZ3: 619506 | BA3: 0 | BB3: 0 | BC3: 0 | BD3: 0 | BE3: 0 | BF3: 0 | BG3: 0 | BH3: 0 | BI3: 28240925 | BJ3: 566358 | BK3: 522790 | BL3: 0 | BM3: 27353408 | BN3: 3543545 | BO3: 0 | BP3: 31986101 | BQ3: 60227026 | BR3: -13906462 | BS3: -1124378 | BT3: -68 | BU3: 0 | BV3: -15030908 | BW3: -2251541 | BX3: -555919 | BY3: -480603 | BZ3: -3288063 | CA3: 41908055 | CB3: 60227026 | CC3: =(BN3+BO3)/CB3*100 -> 5.883646
A4: 3 | B4: Cassava | C4: 0 | D4: 0 | E4: 7591967 | F4: 3728 | G4: 0 | H4: 0 | I4: 0 | J4: 0 | K4: 12372 | L4: 0 | M4: 0 | N4: 0 | O4: 0 | P4: 0 | Q4: 0 | R4: 0 | S4: 53738757 | T4: 0 | U4: 817601 | V4: 609291 | W4: 0 | X4: 0 | Y4: 0 | Z4: 0 | AA4: 0 | AB4: 0 | AC4: 0 | AD4: 0 | AE4: 0 | AF4: 0 | AG4: 0 | AH4: 0 | AI4: 0 | AJ4: 0 | AK4: 0 | AL4: 0 | AM4: 0 | AN4: 0 | AO4: 0 | AP4: 0 | AQ4: 0 | AR4: 0 | AS4: 0 | AT4: 0 | AU4: 0 | AV4: 0 | AW4: 0 | AX4: 0 | AY4: 0 | AZ4: 596998 | BA4: 0 | BB4: 0 | BC4: 0 | BD4: 0 | BE4: 0 | BF4: 0 | BG4: 0 | BH4: 694544 | BI4: 64065258 | BJ4: 522579 | BK4: 380 | BL4: 0 | BM4: 12230209 | BN4: 0 | BO4: 0 | BP4: 12753168 | BQ4: 76818426 | BR4: 0 | BS4: 0 | BT4: 0 | BU4: 0 | BV4: 0 | BW4: -2122820 | BX4: -174398 | BY4: -520955 | BZ4: -2818173 | CA4: 74000253 | CB4: 76818426 | CC4: =(BN4+BO4)/CB4*100 -> 0
A5: 4 | B5: Beans and Nuts | C5: 0 | D5: 0 | E5: 0 | F5: 654864 | G5: 3018992 | H5: 0 | I5: 0 | J5: 0 | K5: 2388736 | L5: 0 | M5: 0 | N5: 0 | O5: 0 | P5: 0 | Q5: 0 | R5: 12724250 | S5: 942118 | T5: 0 | U5: 12346452 | V5: 1388919 | W5: 5136281 | X5: 0 | Y5: 0 | Z5: 0 | AA5: 0 | AB5: 0 | AC5: 0 | AD5: 480022 | AE5: 0 | AF5: 0 | AG5: 0 | AH5: 0 | AI5: 0 | AJ5: 0 | AK5: 0 | AL5: 0 | AM5: 0 | AN5: 0 | AO5: 0 | AP5: 0 | AQ5: 0 | AR5: 0 | AS5: 0 | AT5: 0 | AU5: 0 | AV5: 0 | AW5: 0 | AX5: 0 | AY5: 0 | AZ5: 7520510 | BA5: 0 | BB5: 0 | BC5: 0 | BD5: 0 | BE5: 0 | BF5: 204294 | BG5: 0 | BH5: 609364 | BI5: 47414802 | BJ5: 1221069 | BK5: 109055 | BL5: 0 | BM5: -288257 | BN5: 2149301 | BO5: 0 | BP5: 3191168 | BQ5: 50605970 | BR5: -43130296 | BS5: -928667 | BT5: -15266 | BU5: 0 | BV5: -44074229 | BW5: -1122621 | BX5: -949787 | BY5: -76695 | BZ5: -2149103 | CA5: 4382638 | CB5: 50605970 | CC5: =(BN5+BO5)/CB5*100 -> 4.2471293
A6: 5 | B6: Vegetables and Fruits | C6: 0 | D6: 0 | E6: 0 | F6: 0 | G6: 260340 | H6: 0 | I6: 0 | J6: 0 | K6: 2828602 | L6: 0 | M6: 0 | N6: 0 | O6: 0 | P6: 0 | Q6: 0 | R6: 60639500 | S6: 0 | T6: 0 | U6: 8583443 | V6: 534552 | W6: 7016675 | X6: 0 | Y6: 0 | Z6: 0 | AA6: 0 | AB6: 0 | AC6: 1104460 | AD6: 3988 | AE6: 1435019 | AF6: 0 | AG6: 0 | AH6: 0 | AI6: 0 | AJ6: 0 | AK6: 0 | AL6: 0 | AM6: 0 | AN6: 0 | AO6: 0 | AP6: 0 | AQ6: 0 | AR6: 0 | AS6: 0 | AT6: 0 | AU6: 0 | AV6: 0 | AW6: 0 | AX6: 0 | AY6: 0 | AZ6: 105084676 | BA6: 36428 | BB6: 0 | BC6: 0 | BD6: 0 | BE6: 0 | BF6: 22284008 | BG6: 2821187 | BH6: 1095279 | BI6: 213728157 | BJ6: 586918761 | BK6: 244132 | BL6: 0 | BM6: 0 | BN6: 165985221 | BO6: 2304919 | BP6: 755453033 | BQ6: 969181190 | BR6: -48485134 | BS6: -3764461 | BT6: -96691 | BU6: -1436930 | BV6: -53783216 | BW6: -114494467 | BX6: -139827431 | BY6: -15436605 | BZ6: -269758503 | CA6: 645639471 | CB6: 969181190 | CC6: =(BN6+BO6)/CB6*100 -> 17.364157
A7: 6 | B7: Sugarcane | C7: 0 | D7: 0 | E7: 0 | F7: 0 | G7: 0 | H7: 4490083 | I7: 0 | J7: 0 | K7: 0 | L7: 0 | M7: 0 | N7: 0 | O7: 0 | P7: 0 | Q7: 0 | R7: 0 | S7: 0 | T7: 68681060 | U7: 0 | V7: 0 | W7: 206684 | X7: 0 | Y7: 0 | Z7: 0 | AA7: 0 | AB7: 0 | AC7: 0 | AD7: 2232 | AE7: 0 | AF7: 0 | AG7: 0 | AH7: 0 | AI7: 0 | AJ7: 0 | AK7: 0 | AL7: 0 | AM7: 0 | AN7: 0 | AO7: 0 | AP7: 0 | AQ7: 0 | AR7: 0 | AS7: 0 | AT7: 0 | AU7: 0 | AV7: 0 | AW7: 0 | AX7: 0 | AY7: 0 | AZ7: 0 | BA7: 0 | BB7: 0 | BC7: 0 | BD7: 0 | BE7: 0 | BF7: 0 | BG7: 0 | BH7: 10572 | BI7: 73390631 | BJ7: 7039 | BK7: 0 | BL7: 0 | BM7: 0 | BN7: 96 | BO7: 0 | BP7: 7135 | BQ7: 73397766 | BR7: -2 | BS7: 0 | BT7: 0 | BU7: 0 | BV7: -2 | BW7: -3338345 | BX7: -1849 | BY7: -2252169 | BZ7: -5592363 | CA7: 67805401 | CB7: 73397766 | CC7: =(BN7+BO7)/CB7*100 -> 0.00013079417
A8: 7 | B8: Rubber (Latex) | C8: 0 | D8: 0 | E8: 0 | F8: 0 | G8: 0 | H8: 0 | I8: 9953834 | J8: 0 | K8: 0 | L8: 0 | M8: 0 | N8: 0 | O8: 0 | P8: 0 | Q8: 0 | R8: 0 | S8: 0 | T8: 0 | U8: 0 | V8: 0 | W8: 0 | X8: 0 | Y8: 0 | Z8: 0 | AA8: 0 | AB8: 0 | AC8: 0 | AD8: 0 | AE8: 96766 | AF8: 0 | AG8: 105841640 | AH8: 0 | AI8: 0 | AJ8: 0 | AK8: 0 | AL8: 0 | AM8: 0 | AN8: 0 | AO8: 0 | AP8: 0 | AQ8: 15939 | AR8: 0 | AS8: 0 | AT8: 35200 | AU8: 0 | AV8: 0 | AW8: 0 | AX8: 0 | AY8: 0 | AZ8: 0 | BA8: 0 | BB8: 0 | BC8: 0 | BD8: 0 | BE8: 0 | BF8: 0 | BG8: 0 | BH8: 143396 | BI8: 116086775 | BJ8: 0 | BK8: 15785 | BL8: 0 | BM8: 67637322 | BN8: 52033737 | BO8: 0 | BP8: 119686844 | BQ8: 235773619 | BR8: -140664 | BS8: 0 | BT8: -8803 | BU8: 0 | BV8: -149467 | BW8: -13165354 | BX8: 0 | BY8: -1416395 | BZ8: -14581749 | CA8: 221042403 | CB8: 235773619 | CC8: =(BN8+BO8)/CB8*100 -> 22.069363
A9: 8 | B9: Other Crops | C9: 16110576 | D9: 829269 | E9: 1504441 | F9: 357001 | G9: 50313291 | H9: 3021059 | I9: 2246407 | J9: 14706240 | K9: 848308 | L9: 334330 | M9: 440057 | N9: 0 | O9: 0 | P9: 0 | Q9: 0 | R9: 85851714 | S9: 13343855 | T9: 255049 | U9: 8856829 | V9: 255989 | W9: 28781423 | X9: 1479335 | Y9: 89683 | Z9: 12982 | AA9: 3128 | AB9: 0 | AC9: 0 | AD9: 163081 | AE9: 8090848 | AF9: 0 | AG9: 0 | AH9: 0 | AI9: 0 | AJ9: 0 | AK9: 0 | AL9: 0 | AM9: 0 | AN9: 0 | AO9: 0 | AP9: 0 | AQ9: 0 | AR9: 0 | AS9: 255123 | AT9: 160203 | AU9: 0 | AV9: 0 | AW9: 33565 | AX9: 1353797 | AY9: 0 | AZ9: 2046837 | BA9: 0 | BB9: 0 | BC9: 0 | BD9: 1997 | BE9: 402488 | BF9: 170045 | BG9: 1951087 | BH9: 476099 | BI9: 244746136 | BJ9: 3944695 | BK9: 2199489 | BL9: 0 | BM9: 203793 | BN9: 27642715 | BO9: 0 | BP9: 33990692 | BQ9: 278736828 | BR9: -51624855 | BS9: -1700242 | BT9: -444317 | BU9: -5001 | BV9: -53774415 | BW9: -14993310 | BX9: -8180463 | BY9: -3058595 | BZ9: -26232368 | CA9: 198730045 | CB9: 278736828 | CC9: =(BN9+BO9)/CB9*100 -> 9.9171377
A10: 9 | B10: Livestock | C10: 0 | D10: 0 | E10: 0 | F10: 0 | G10: 649482 | H10: 0 | I10: 0 | J10: 10772 | K10: 27489559 | L10: 0 | M10: 0 | N10: 0 | O10: 0 | P10: 0 | Q10: 300253373 | R10: 19003354 | S10: 0 | T10: 0 | U10: 4161915 | V10: 0 | W10: 0 | X10: 0 | Y10: 6667100 | Z10: 18311 | AA10: 0 | AB10: 0 | AC10: 0 | AD10: 284322 | AE10: 829987 | AF10: 0 | AG10: 0 | AH10: 0 | AI10: 0 | AJ10: 0 | AK10: 0 | AL10: 0 | AM10: 0 | AN10: 0 | AO10: 0 | AP10: 0 | AQ10: 0 | AR10: 1313067 | AS10: 0 | AT10: 25524 | AU10: 0 | AV10: 0 | AW10: 0 | AX10: 0 | AY10: 0 | AZ10: 7016546 | BA10: 0 | BB10: 0 | BC10: 0 | BD10: 0 | BE10: 0 | BF10: 1403526 | BG10: 36415 | BH10: 147330 | BI10: 369310583 | BJ10: 75750243 | BK10: 537858 | BL10: 3049362 | BM10: 0 | BN10: 15461511 | BO10: 0 | BP10: 94798974 | BQ10: 464109557 | BR10: -5602028 | BS10: -3501 | BT10: -128344 | BU10: 0 | BV10: -5733873 | BW10: -36985660 | BX10: -4414998 | BY10: -2394924 | BZ10: -43795582 | CA10: 414580102 | CB10: 464109557 | CC10: =(BN10+BO10)/CB10*100 -> 3.3314356
A11: 10 | B11: Forestry | C11: 4505 | D11: 0 | E11: 0 | F11: 0 | G11: 95611 | H11: 0 | I11: 0 | J11: 6674 | K11: 136453 | L11: 700494 | M11: 8062 | N11: 0 | O11: 0 | P11: 132475 | Q11: 0 | R11: 43408 | S11: 0 | T11: 15218 | U11: 845776 | V11: 23963 | W11: 33440 | X11: 5016 | Y11: 0 | Z11: 0 | AA11: 6063713 | AB11: 0 | AC11: 0 | AD11: 15938 | AE11: 1275852 | AF11: 0 | AG11: 110393 | AH11: 0 | AI11: 0 | AJ11: 127132 | AK11: 0 | AL11: 0 | AM11: 0 | AN11: 0 | AO11: 0 | AP11: 0 | AQ11: 7227 | AR11: 0 | AS11: 38887303 | AT11: 22766 | AU11: 345213 | AV11: 0 | AW11: 1147176 | AX11: 359353 | AY11: 0 | AZ11: 1066145 | BA11: 0 | BB11: 0 | BC11: 0 | BD11: 0 | BE11: 0 | BF11: 20510 | BG11: 0 | BH11: 336145 | BI11: 51835961 | BJ11: 10481989 | BK11: 0 | BL11: 0 | BM11: -38847602 | BN11: 9694480 | BO11: 0 | BP11: -18671133 | BQ11: 33164828 | BR11: -2716606 | BS11: -12523 | BT11: -202643 | BU11: 0 | BV11: -2931772 | BW11: -4021847 | BX11: -1697316 | BY11: -479105 | BZ11: -6198268 | CA11: 24034788 | CB11: 33164828 | CC11: =(BN11+BO11)/CB11*100 -> 29.231208
A12: 11 | B12: Fishery | C12: 0 | D12: 0 | E12: 0 | F12: 0 | G12: 0 | H12: 0 | I12: 0 | J12: 0 | K12: 4224945 | L12: 0 | M12: 11719193 | N12: 0 | O12: 0 | P12: 0 | Q12: 0 | R12: 82007018 | S12: 0 | T12: 0 | U12: 3173024 | V12: 2091654 | W12: 0 | X12: 0 | Y12: 0 | Z12: 0 | AA12: 0 | AB12: 0 | AC12: 0 | AD12: 0 | AE12: 4175208 | AF12: 0 | AG12: 0 | AH12: 0 | AI12: 0 | AJ12: 0 | AK12: 0 | AL12: 0 | AM12: 0 | AN12: 0 | AO12: 0 | AP12: 0 | AQ12: 0 | AR12: 0 | AS12: 0 | AT12: 0 | AU12: 0 | AV12: 0 | AW12: 0 | AX12: 0 | AY12: 0 | AZ12: 53290815 | BA12: 0 | BB12: 0 | BC12: 0 | BD12: 0 | BE12: 0 | BF12: 3605291 | BG12: 157531 | BH12: 238845 | BI12: 164683524 | BJ12: 107290773 | BK12: 141201 | BL12: 3154870 | BM12: 0 | BN12: 4047601 | BO12: 0 | BP12: 114634445 | BQ12: 279317969 | BR12: -11276066 | BS12: -108065 | BT12: -19107 | BU12: 0 | BV12: -11403238 | BW12: -31308028 | BX12: -31178009 | BY12: -5422074 | BZ12: -67908111 | CA12: 200006620 | CB12: 279317969 | CC12: =(BN12+BO12)/CB12*100 -> 1.4491015
A13: 12 | B13: Crude Oil and Coal | C13: 0 | D13: 0 | E13: 0 | F13: 0 | G13: 0 | H13: 0 | I13: 0 | J13: 0 | K13: 0 | L13: 0 | M13: 0 | N13: 15879688 | O13: 0 | P13: 0 | Q13: 0 | R13: 0 | S13: 0 | T13: 0 | U13: 0 | V13: 0 | W13: 0 | X13: 0 | Y13: 0 | Z13: 0 | AA13: 0 | AB13: 0 | AC13: 3145740 | AD13: 0 | AE13: 7013921 | AF13: 807407767 | AG13: 0 | AH13: 0 | AI13: 7448520 | AJ13: 0 | AK13: 0 | AL13: 5289759 | AM13: 0 | AN13: 0 | AO13: 0 | AP13: 0 | AQ13: 0 | AR13: 0 | AS13: 0 | AT13: 0 | AU13: 401159406 | AV13: 0 | AW13: 0 | AX13: 0 | AY13: 0 | AZ13: 0 | BA13: 0 | BB13: 0 | BC13: 0 | BD13: 0 | BE13: 0 | BF13: 0 | BG13: 0 | BH13: 87013 | BI13: 1247431814 | BJ13: 0 | BK13: 0 | BL13: 0 | BM13: 119611124 | BN13: 15399283 | BO13: 0 | BP13: 135010407 | BQ13: 1382442221 | BR13: -935241246 | BS13: 0 | BT13: -79102992 | BU13: 0 | BV13: -1014344238 | BW13: -877229 | BX13: 0 | BY13: -819088 | BZ13: -1696317 | CA13: 366401666 | CB13: 1382442221 | CC13: =(BN13+BO13)/CB13*100 -> 1.1139187
... A60: 190 | B60: Total Intermedite Transaction | C60: 106906674 | D60: 16923776 | E60: 26099879 | F60: 2062686 | G60: 239251631 | H60: 28326762 | I60: 50993258 | J60: 80466542 | K60: 224589912 | L60: 6037452 | M60: 101679877 | N60: 144695129 | O60: 101932 | P60: 54795133 | Q60: 345592022 | R60: 610662137 | S60: 425142761 | T60: 92812194 | U60: 214128989 | V60: 58891734 | W60: 292450233 | X60: 10592862 | Y60: 124948797 | Z60: 200384361 | AA60: 140145752 | AB60: 53246623 | AC60: 556724292 | AD60: 52473965 | AE60: 318116496 | AF60: 964139721 | AG60: 273556458 | AH60: 357430771 | AI60: 131262408 | AJ60: 190601782 | AK60: 199798869 | AL60: 82274692 | AM60: 334841045 | AN60: 402788746 | AO60: 2641849482 | AP60: 1568170254 | AQ60: 66076851 | AR60: 59496577 | AS60: 159521558 | AT60: 950128273 | AU60: 1054356045 | AV60: 24539836 | AW60: 473984576 | AX60: 471271482 | AY60: 885263498 | AZ60: 875765624 | BA60: 814403852 | BB60: 220025772 | BC60: 542128847 | BD60: 159728075 | BE60: 774493305 | BF60: 693426474 | BG60: 478251118 | BH60: 135398550 | BI60: 20564218402 | BJ60: 8786511895 | BK60: 2951397062 | BL60: 3803228016 | BM60: 859985000 | BN60: 8568939920 | BO60: 813739550 | BP60: 25783801443 | BQ60: 46348019845 | BR60: -8525584600 | BS60: -102067001 | BT60: -412509295 | BU60: -1006557745 | BV60: -10046718641 | BW60: 0 | BX60: 0 | BY60: 0 | BZ60: 0 | CA60: 36301301204 | CB60: 46348019845 | CC60: =(BN60+BO60)/CB60*100 -> 20.243971
A61: 201 | B61: Wages and Salaries | C61: 66711643 | D61: 10628282 | E61: 18683997 | F61: 767311 | G61: 136013312 | H61: 18783938 | I61: 64784079 | J61: 35413750 | K61: 50686440 | L61: 6320044 | M61: 26891695 | N61: 42087971 | O61: 22061 | P61: 19573576 | Q61: 49425595 | R61: 39310178 | S61: 27530408 | T61: 16567714 | U61: 25110263 | V61: 3185990 | W61: 28569844 | X61: 2936191 | Y61: 17141312 | Z61: 29888490 | AA61: 16018297 | AB61: 8521990 | AC61: 86118488 | AD61: 5605242 | AE61: 46699106 | AF61: 19313941 | AG61: 23030390 | AH61: 47442202 | AI61: 21976498 | AJ61: 29329386 | AK61: 18482114 | AL61: 19138116 | AM61: 53518694 | AN61: 52341917 | AO61: 211962643 | AP61: 182634401 | AQ61: 14952073 | AR61: 9470241 | AS61: 36677620 | AT61: 102883422 | AU61: 124771661 | AV61: 12984883 | AW61: 41787909 | AX61: 92574143 | AY61: 647824586 | AZ61: 127021412 | BA61: 112659098 | BB61: 111491741 | BC61: 376967948 | BD61: 56449574 | BE61: 157051770 | BF61: 1568187883 | BG61: 195459789 | BH61: 34338703 | BI61: 5402721965 | CC61: =(BN61+BO61)/CB61*100 -> #DIV/0!
A62: 202 | B62: Operating Surplus | C62: 103830453 | D62: 12857217 | E62: 26105667 | F62: 1495111 | G62: 236904462 | H62: 28074623 | I62: 97839571 | J62: 74033448 | K62: 118896569 | L62: 9645342 | M62: 50955088 | N62: 73605379 | O62: 46442 | P62: 40933335 | Q62: 101568841 | R62: 65093679 | S62: 42181828 | T62: 26116643 | U62: 41579323 | V62: 5546964 | W62: 55224412 | X62: 5869258 | Y62: 25551965 | Z62: 37597366 | AA62: 26432469 | AB62: 9746331 | AC62: 113625088 | AD62: 7866354 | AE62: 66058854 | AF62: 17259410 | AG62: 37332756 | AH62: 54828558 | AI62: 34399811 | AJ62: 34035645 | AK62: 26131144 | AL62: 24360395 | AM62: 83521995 | AN62: 70657723 | AO62: 320472134 | AP62: 207807404 | AQ62: 22816474 | AR62: 11479631 | AS62: 48466444 | AT62: 151097808 | AU62: 160731710 | AV62: 15125897 | AW62: 53817134 | AX62: 117461623 | AY62: 1316903123 | AZ62: 151103069 | BA62: 137626748 | BB62: 134587008 | BC62: 568994615 | BD62: 100405038 | BE62: 200100257 | BF62: 178554120 | BG62: 172036260 | BH62: 66417821 | BI62: 6023813837 | CC62: =(BN62+BO62)/CB62*100 -> #DIV/0!
A63: 203 | B63: Depreciation | C63: 23207172 | D63: 1477950 | E63: 3073928 | F63: 55352 | G63: 33149151 | H63: 7826419 | I63: 7305765 | J63: 8717527 | K63: 19729403 | L63: 1414583 | M63: 20353707 | N63: 64631360 | O63: 13759 | P63: 10081721 | Q63: 26345577 | R63: 33751869 | S63: 18849197 | T63: 16007977 | U63: 16841816 | V63: 2177845 | W63: 29391696 | X63: 1342188 | Y63: 16210599 | Z63: 15295478 | AA63: 13748888 | AB63: 5121897 | AC63: 58052753 | AD63: 2782923 | AE63: 28547955 | AF63: 57550155 | AG63: 23223244 | AH63: 30645892 | AI63: 14237400 | AJ63: 21217832 | AK63: 9025763 | AL63: 7725868 | AM63: 24961642 | AN63: 33787543 | AO63: 153620165 | AP63: 108764737 | AQ63: 6793652 | AR63: 4893238 | AS63: 15956666 | AT63: 61092259 | AU63: 167999545 | AV63: 16099776 | AW63: 34180226 | AX63: 65629867 | AY63: 351052090 | AZ63: 99217482 | BA63: 117734997 | BB63: 105107866 | BC63: 135087385 | BD63: 316387538 | BE63: 73000455 | BF63: 394879485 | BG63: 74676300 | BH63: 30542477 | BI63: 3040598000 | CC63: =(BN63+BO63)/CB63*100 -> #DIV/0!
A64: 204 | B64: Indirect Taxes less Subsidies | C64: 149515 | D64: 20830 | E64: 36782 | F64: 2178 | G64: 320915 | H64: -15206341 | I64: 119730 | J64: 98778 | K64: 677778 | L64: 617367 | M64: 126253 | N64: 41381827 | O64: 4753 | P64: 3236017 | Q64: 5776573 | R64: 22090987 | S64: 13128977 | T64: -1373182 | U64: 6513021 | V64: 1506350 | W64: 152310138 | X64: 29375406 | Y64: 3967570 | Z64: 8664710 | AA64: 4237165 | AB64: 1678479 | AC64: 20642223 | AD64: 1511548 | AE64: 13334411 | AF64: 204210841 | AG64: 8217988 | AH64: 10581774 | AI64: 4356519 | AJ64: 6449318 | AK64: 8315757 | AL64: 4924091 | AM64: 13275908 | AN64: 15140477 | AO64: 79347221 | AP64: 115825059 | AQ64: 2387607 | AR64: 2148117 | AS64: 5624269 | AT64: 28174403 | AU64: 32533488 | AV64: 2513142 | AW64: 8943455 | AX64: 11176160 | AY64: 85282953 | AZ64: 39525716 | BA64: 25199552 | BB64: 12593641 | BC64: 103782658 | BD64: 18624255 | BE64: 29403529 | BF64: 8993207 | BG64: 61751904 | BH64: 5695233 | BI64: 1269949000 | CC64: =(BN64+BO64)/CB64*100 -> #DIV/0!
A65: 209 | B65: Total Value Added | C65: 193898783 | D65: 24984279 | E65: 47900374 | F65: 2319952 | G65: 406387840 | H65: 39478639 | I65: 170049145 | J65: 118263503 | K65: 189990190 | L65: 17997336 | M65: 98326743 | N65: 221706537 | O65: 87015 | P65: 73824649 | Q65: 183116586 | R65: 160246713 | S65: 101690410 | T65: 57319152 | U65: 90044423 | V65: 12417149 | W65: 265496090 | X65: 39523043 | Y65: 62871446 | Z65: 91446044 | AA65: 60436819 | AB65: 25068697 | AC65: 278438552 | AD65: 17766067 | AE65: 154640326 | AF65: 298334347 | AG65: 91804378 | AH65: 143498426 | AI65: 74970228 | AJ65: 91032181 | AK65: 61954778 | AL65: 56148470 | AM65: 175278239 | AN65: 171927660 | AO65: 765402163 | AP65: 615031601 | AQ65: 46949806 | AR65: 27991227 | AS65: 106724999 | AT65: 343247892 | AU65: 486036404 | AV65: 46723698 | AW65: 138728724 | AX65: 286841793 | AY65: 2401062752 | AZ65: 416867679 | BA65: 393220395 | BB65: 363780256 | BC65: 1184832606 | BD65: 491866405 | BE65: 459556011 | BF65: 2150614695 | BG65: 503924253 | BH65: 136994234 | BI65: 15737082802 | CC65: =(BN65+BO65)/CB65*100 -> #DIV/0!
A66: 210 | B66: Control Total | C66: 300805457 | D66: 41908055 | E66: 74000253 | F66: 4382638 | G66: 645639471 | H66: 67805401 | I66: 221042403 | J66: 198730045 | K66: 414580102 | L66: 24034788 | M66: 200006620 | N66: 366401666 | O66: 188947 | P66: 128619782 | Q66: 528708608 | R66: 770908850 | S66: 526833171 | T66: 150131346 | U66: 304173412 | V66: 71308883 | W66: 557946323 | X66: 50115905 | Y66: 187820243 | Z66: 291830405 | AA66: 200582571 | AB66: 78315320 | AC66: 835162844 | AD66: 70240032 | AE66: 472756822 | AF66: 1262474068 | AG66: 365360836 | AH66: 500929197 | AI66: 206232636 | AJ66: 281633963 | AK66: 261753647 | AL66: 138423162 | AM66: 510119284 | AN66: 574716406 | AO66: 3407251645 | AP66: 2183201855 | AQ66: 113026657 | AR66: 87487804 | AS66: 266246557 | AT66: 1293376165 | AU66: 1540392449 | AV66: 71263534 | AW66: 612713300 | AX66: 758113275 | AY66: 3286326250 | AZ66: 1292633303 | BA66: 1207624247 | BB66: 583806028 | BC66: 1726961453 | BD66: 651594480 | BE66: 1234049316 | BF66: 2844041169 | BG66: 982175371 | BH66: 272392784 | BI66: 36301301204 | CC66: =(BN66+BO66)/CB66*100 -> #DIV/0!
A67: Grand Total | C67: 902416371 | D67: 125724165 | E67: 222000759 | F67: 13147914 | G67: 1936918413 | H67: 203416203 | I67: 663127209 | J67: 596190135 | K67: 1243740306 | L67: 72104364 | M67: 600019860 | N67: 1099204998 | O67: 566841 | P67: 385859346 | Q67: 1586125824 | R67: 2312726550 | S67: 1580499513 | T67: 450394038 | U67: 912520236 | V67: 213926649 | W67: 1673838969 | X67: 150347715 | Y67: 563460729 | Z67: 875491215 | AA67: 601747713 | AB67: 234945960 | AC67: 2505488532 | AD67: 210720096 | AE67: 1418270466 | AF67: 3787422204 | AG67: 1096082508 | AH67: 1502787591 | AI67: 618697908 | AJ67: 844901889 | AK67: 785260941 | AL67: 415269486 | AM67: 1530357852 | AN67: 1724149218 | AO67: 10221754935 | AP67: 6549605565 | AQ67: 339079971 | AR67: 262463412 | AS67: 798739671 | AT67: 3880128495 | AU67: 4621177347 | AV67: 213790602 | AW67: 1838139900 | AX67: 2274339825 | AY67: 9858978750 | AZ67: 3877899909 | BA67: 3622872741 | BB67: 1751418084 | BC67: 5180884359 | BD67: 1954783440 | BE67: 3702147948 | BF67: 8532123507 | BG67: 2946526113 | BH67: 817178352 | BI67: 108903903612 | BJ67: 17573023790 | BK67: 5902794124 | BL67: 7606456032 | BM67: 1719970000 | BN67: 17137879840 | BO67: 1627479100 | BP67: 51567602886 | BQ67: 92696039690 | BR67: -17051169200 | BS67: -204134002 | BT67: -825018590 | BU67: -2013115490 | BV67: -20093437282 | BW67: 0 | BX67: 0 | BY67: 0 | BZ67: 0 | CA67: 72602602408 | CB67: 92696039690 | CC67: =(BN67+BO67)/CB67*100 -> 20.243971

Sheet Sheet2
C2: Output | D2: Exports
B3: Paddy | C3: 314114660 | D3: 15619
B4: Maize | C4: 60227026 | D4: 3543545
B5: Cassava | C5: 76818426 | D5: 0
B6: Beans and Nuts | C6: 50605970 | D6: 2149301
B7: Vegetables and Fruits | C7: 969181190 | D7: 168290140
B8: Sugarcane | C8: 73397766 | D8: 96
B9: Rubber (Latex) | C9: 235773619 | D9: 52033737
B10: Other Crops | C10: 278736828 | D10: 27642715
B11: Livestock | C11: 464109557 | D11: 15461511
B12: Forestry | C12: 33164828 | D12: 9694480
B13: Fishery | C13: 279317969 | D13: 4047601
B14: Crude Oil and Coal | C14: 1382442221 | D14: 15399283
... B60: Unclassified | C60: 294303940 | D60: 7791194

Sheet Export orient
C1: Exports in total output
C2: 1990 | D2: 2021 | E2: Share in output | G2: change 2021-1990 | H2: Share in output | K2: change 2021-1990
A3: 1 | B3: Paddy | C3: =[1]Sheet3!CD3 -> 0 | D3: =proc!CC2 -> 0.0049723881 | E3: 0.67773049 | F3: =B3 -> Paddy | G3: =D3-C3 -> 0.0049723881 | H3: =(proc!CB2/proc!$CB$60)*100 -> 0.67773049 | J3: Animal Food | K3: 43.204526
A4: 2 | B4: Maize | C4: =[1]Sheet3!CD4 -> 34.731174 | D4: =proc!CC3 -> 5.883646 | E4: 0.1299452 | F4: =B4 -> Maize | G4: =D4-C4 -> -28.847528 | H4: =(proc!CB3/proc!$CB$60)*100 -> 0.1299452 | J4: Basic Chemical Products | K4: 39.416439
A5: 3 | B5: Cassava | C5: =[1]Sheet3!CD5 -> 2.1530531 | D5: =proc!CC4 -> 0 | E5: 0.16574263 | F5: =B5 -> Cassava | G5: =D5-C5 -> -2.1530531 | H5: =(proc!CB4/proc!$CB$60)*100 -> 0.16574263 | J5: Industrial Machinery | K5: 34.137211
A6: 4 | B6: Beans and Nuts | C6: =[1]Sheet3!CD6 -> 24.47894 | D6: =proc!CC5 -> 4.2471293 | E6: 0.10918691 | F6: =B6 -> Beans and Nuts | G6: =D6-C6 -> -20.23181 | H6: =(proc!CB5/proc!$CB$60)*100 -> 0.10918691 | J6: Motor Vehicles and Repairing | K6: 33.311405
A7: 5 | B7: Vegetables and Fruits | C7: =[1]Sheet3!CD7 -> 2.9093712 | D7: =proc!CC6 -> 17.364157 | E7: 2.0910951 | F7: =B7 -> Vegetables and Fruits | G7: =D7-C7 -> 14.454785 | H7: =(proc!CB6/proc!$CB$60)*100 -> 2.0910951 | J7: Rubber Products | K7: 28.886018
A8: 6 | B8: Sugarcane | C8: =[1]Sheet3!CD8 -> 0.00033944754 | D8: =proc!CC7 -> 0.00013079417 | E8: 0.15836225 | F8: =B8 -> Sugarcane | G8: =D8-C8 -> -0.00020865337 | H8: =(proc!CB7/proc!$CB$60)*100 -> 0.15836225 | J8: Forestry | K8: 27.114906
A9: 7 | B9: Rubber (Latex) | C9: =[1]Sheet3!CD9 -> 6.2934438 | D9: =proc!CC8 -> 22.069363 | E9: 0.50870268 | F9: =B9 -> Rubber (Latex) | G9: =D9-C9 -> 15.77592 | H9: =(proc!CB8/proc!$CB$60)*100 -> 0.50870268 | J9: Spinning, Weaving and Bleaching | K9: 18.470099
A10: 8 | B10: Other Crops | C10: =[1]Sheet3!CD10 -> 7.5780693 | D10: =proc!CC9 -> 9.9171377 | E10: 0.60139965 | F10: =B10 -> Other Crops | G10: =D10-C10 -> 2.3390683 | H10: =(proc!CB9/proc!$CB$60)*100 -> 0.60139965 | J10: Saw Mills and Wood Products | K10: 18.429415
A11: 9 | B11: Livestock | C11: =[1]Sheet3!CD11 -> 0.96855177 | D11: =proc!CC10 -> 3.3314356 | E11: 1.0013579 | F11: =B11 -> Livestock | G11: =D11-C11 -> 2.3628838 | H11: =(proc!CB10/proc!$CB$60)*100 -> 1.0013579 | J11: Paper and Paper Products | K11: 17.159079
A12: 10 | B12: Forestry | C12: =[1]Sheet3!CD12 -> 2.116302 | D12: =proc!CC11 -> 29.231208 | E12: 0.071556084 | F12: =B12 -> Forestry | G12: =D12-C12 -> 27.114906 | H12: =(proc!CB11/proc!$CB$60)*100 -> 0.071556084 | J12: Non-ferrous Metal | K12: 17.113699
A13: 11 | B13: Fishery | C13: =[1]Sheet3!CD13 -> 1.3100587 | D13: =proc!CC12 -> 1.4491015 | E13: 0.60265351 | F13: =B13 -> Fishery | G13: =D13-C13 -> 0.13904284 | H13: =(proc!CB12/proc!$CB$60)*100 -> 0.60265351 | J13: Petroleum Refineries | K13: 15.885995
A14: 12 | B14: Crude Oil and Coal | C14: =[1]Sheet3!CD14 -> 4.0154679 | D14: =proc!CC13 -> 1.1139187 | E14: 2.9827428 | F14: =B14 -> Crude Oil and Coal | G14: =D14-C14 -> -2.9015491 | H14: =(proc!CB13/proc!$CB$60)*100 -> 2.9827428 | J14: Rubber (Latex) | K14: 15.77592
... A59: 57 | B59: Other Services | C59: =[1]Sheet3!CD59 -> 4.5851018 | D59: =proc!CC58 -> 4.3502752 | E59: 2.1555439 | F59: =B59 -> Other Services | G59: =D59-C59 -> -0.23482653 | H59: =(proc!CB58/proc!$CB$60)*100 -> 2.1555439 | J59: Maize | K59: -28.847528
B61: Total | C61: =[1]Sheet3!CD61 -> 13.318831 | D61: =proc!CC60 -> 20.243971
C68: Exports in total output
C69: 1990 | D69: 2021 | E69: Share in output
B70: Electrical Equipment | C70: 29.473383 | D70: 36.078763 | E70: 13.016094 | F70: 0.2
B71: Motor Vehicles | C71: 1.2050082 | D71: 34.516413 | E71: 6.4240725 | F71: 0.2
B74: Finance and Insurance | C74: 0.43126808 | D74: 2.2978043 | E74: 3.9023701 | F74: 0.2
B75: Petroleum Products | C75: 2.4440385 | D75: 18.330033 | E75: 3.7325001 | F75: 0.2
B77: Basic Chemicals | C77: 3.5493754 | D77: 42.965815 | E77: 3.6179936 | F77: 0.2
B78: Business Activities | C78: 11.979068 | D78: 8.3749407 | E78: 3.3490597 | F78: 0.2
B80: Hotels and Restaurants | C80: 19.171882 | D80: 7.5412801 | E80: 2.9307266 | F80: 0.2
B81: Machinery | C81: 2.0898027 | D81: 36.227013 | E81: 2.8160168 | F81: 0.2
B82: Food Processing | C82: 51.271283 | D82: 40.81772 | E82: 2.4283465 | F82: 0.2
B83: Other Chemicals | C83: 4.6761941 | D83: 16.384195 | E83: 2.3541791 | F83: 0.2
B84: Transport | C84: 25.40369 | D84: 24.381219 | E84: 2.2204351 | F84: 0.2
B86: Fruit and Vegetables | C86: 2.9093712 | D86: 17.364157 | E86: 2.0910951 | F86: 0.2
... B89: Non-Ferrous Metals | C89: 7.6428733 | D89: 24.756573 | E89: 1.9000697 | F89: 0.2

Sheet Sheet1

Sheet processed
A1: INPUT - OUTPUT TABLE OF THAILAND 2021 (58 Sectors) | R1: 1 | S1: Paddy
A2: ROW | B2: Row label | C2: COLUMN | D2: Column label | E2: PURCHASER | F2: WHOLESALE | G2: RETAIL | H2: TRANSPORT | I2: IMPORT | R2: 2 | S2: Maize
A3: 1 | B3: =VLOOKUP(A3,R:S,2,0) -> Paddy | C3: 1 | D3: =VLOOKUP(C3,R:S,2,0) -> Paddy | E3: 23826912 | F3: 0 | G3: 0 | H3: 119524 | I3: 5 | R3: 3 | S3: Cassava
A4: 2 | B4: =VLOOKUP(A4,R:S,2,0) -> Maize | C4: 1 | D4: =VLOOKUP(C4,R:S,2,0) -> Paddy | E4: 0 | F4: 0 | G4: 0 | H4: 0 | I4: 0 | R4: 4 | S4: Beans and Nuts
A5: 3 | B5: =VLOOKUP(A5,R:S,2,0) -> Cassava | C5: 1 | D5: =VLOOKUP(C5,R:S,2,0) -> Paddy | E5: 0 | F5: 0 | G5: 0 | H5: 0 | I5: 0 | R5: 5 | S5: Vegetables and Fruits
A6: 4 | B6: =VLOOKUP(A6,R:S,2,0) -> Beans and Nuts | C6: 1 | D6: =VLOOKUP(C6,R:S,2,0) -> Paddy | E6: 0 | F6: 0 | G6: 0 | H6: 0 | I6: 0 | R6: 6 | S6: Sugarcane
A7: 5 | B7: =VLOOKUP(A7,R:S,2,0) -> Vegetables and Fruits | C7: 1 | D7: =VLOOKUP(C7,R:S,2,0) -> Paddy | E7: 0 | F7: 0 | G7: 0 | H7: 0 | I7: 0 | R7: 7 | S7: Rubber (Latex)
A8: 6 | B8: =VLOOKUP(A8,R:S,2,0) -> Sugarcane | C8: 1 | D8: =VLOOKUP(C8,R:S,2,0) -> Paddy | E8: 0 | F8: 0 | G8: 0 | H8: 0 | I8: 0 | R8: 8 | S8: Other Crops
A9: 7 | B9: =VLOOKUP(A9,R:S,2,0) -> Rubber (Latex) | C9: 1 | D9: =VLOOKUP(C9,R:S,2,0) -> Paddy | E9: 0 | F9: 0 | G9: 0 | H9: 0 | I9: 0 | R9: 9 | S9: Livestock
A10: 8 | B10: =VLOOKUP(A10,R:S,2,0) -> Other Crops | C10: 1 | D10: =VLOOKUP(C10,R:S,2,0) -> Paddy | E10: 16110576 | F10: 0 | G10: 0 | H10: 0 | I10: 0 | R10: 10 | S10: Forestry
A11: 9 | B11: =VLOOKUP(A11,R:S,2,0) -> Livestock | C11: 1 | D11: =VLOOKUP(C11,R:S,2,0) -> Paddy | E11: 0 | F11: 0 | G11: 0 | H11: 0 | I11: 0 | R11: 11 | S11: Fishery
A12: 10 | B12: =VLOOKUP(A12,R:S,2,0) -> Forestry | C12: 1 | D12: =VLOOKUP(C12,R:S,2,0) -> Paddy | E12: 4505 | F12: 19 | G12: 63 | H12: 97 | I12: 0 | R12: 12 | S12: Crude Oil and Coal
A13: 11 | B13: =VLOOKUP(A13,R:S,2,0) -> Fishery | C13: 1 | D13: =VLOOKUP(C13,R:S,2,0) -> Paddy | E13: 0 | F13: 0 | G13: 0 | H13: 0 | I13: 0 | R13: 13 | S13: Metal Ore
A14: 12 | B14: =VLOOKUP(A14,R:S,2,0) -> Crude Oil and Coal | C14: 1 | D14: =VLOOKUP(C14,R:S,2,0) -> Paddy | E14: 0 | F14: 0 | G14: 0 | H14: 0 | I14: 0 | R14: 14 | S14: Non-Metal Ore
... A84: 17 | B84: =VLOOKUP(A84,R:S,2,0) -> Rice and Other Grain Milling | C84: 2 | D84: =VLOOKUP(C84,R:S,2,0) -> Maize | E84: 0 | F84: 0 | G84: 0 | H84: 0 | I84: 0 | R84: 700 | S84: Total Supply
A85: 18 | B85: =VLOOKUP(A85,R:S,2,0) -> Sugar Refineries | C85: 2 | D85: =VLOOKUP(C85,R:S,2,0) -> Maize | E85: 0 | F85: 0 | G85: 0 | H85: 0 | I85: 0
A86: 19 | B86: =VLOOKUP(A86,R:S,2,0) -> Other Foods | C86: 2 | D86: =VLOOKUP(C86,R:S,2,0) -> Maize | E86: 0 | F86: 0 | G86: 0 | H86: 0 | I86: 0
A87: 20 | B87: =VLOOKUP(A87,R:S,2,0) -> Animal Food | C87: 2 | D87: =VLOOKUP(C87,R:S,2,0) -> Maize | E87: 0 | F87: 0 | G87: 0 | H87: 0 | I87: 0
A88: 21 | B88: =VLOOKUP(A88,R:S,2,0) -> Beverages | C88: 2 | D88: =VLOOKUP(C88,R:S,2,0) -> Maize | E88: 0 | F88: 0 | G88: 0 | H88: 0 | I88: 0
A89: 22 | B89: =VLOOKUP(A89,R:S,2,0) -> Tobacco Processing and Products | C89: 2 | D89: =VLOOKUP(C89,R:S,2,0) -> Maize | E89: 0 | F89: 0 | G89: 0 | H89: 0 | I89: 0
A90: 23 | B90: =VLOOKUP(A90,R:S,2,0) -> Spinning, Weaving and Bleaching | C90: 2 | D90: =VLOOKUP(C90,R:S,2,0) -> Maize | E90: 0 | F90: 0 | G90: 0 | H90: 0 | I90: 0
A91: 24 | B91: =VLOOKUP(A91,R:S,2,0) -> Textile Products | C91: 2 | D91: =VLOOKUP(C91,R:S,2,0) -> Maize | E91: 208864 | F91: 40304 | G91: 4800 | H91: 1843 | I91: 0
A92: 25 | B92: =VLOOKUP(A92,R:S,2,0) -> Paper and Paper Products | C92: 2 | D92: =VLOOKUP(C92,R:S,2,0) -> Maize | E92: 554 | F92: 22 | G92: 16 | H92: 5 | I92: 0
A93: 26 | B93: =VLOOKUP(A93,R:S,2,0) -> Printing and Publishing | C93: 2 | D93: =VLOOKUP(C93,R:S,2,0) -> Maize | E93: 0 | F93: 0 | G93: 0 | H93: 0 | I93: 0
A94: 27 | B94: =VLOOKUP(A94,R:S,2,0) -> Basic Chemical Products | C94: 2 | D94: =VLOOKUP(C94,R:S,2,0) -> Maize | E94: 0 | F94: 0 | G94: 0 | H94: 0 | I94: 0
A95: 28 | B95: =VLOOKUP(A95,R:S,2,0) -> Fertilizer and Pesticides | C95: 2 | D95: =VLOOKUP(C95,R:S,2,0) -> Maize | E95: 6761322 | F95: 768586 | G95: 727783 | H95: 290677 | I95: 3881156
A96: 29 | B96: =VLOOKUP(A96,R:S,2,0) -> Other Chemical Products | C96: 2 | D96: =VLOOKUP(C96,R:S,2,0) -> Maize | E96: 0 | F96: 0 | G96: 0 | H96: 0 | I96: 0
... A4958: 190 | B4958: =VLOOKUP(A4958,R:S,2,0) -> Total Intermedite Transaction | C4958: 700 | D4958: =VLOOKUP(C4958,R:S,2,0) -> Total Supply | E4958: 46348019845 | F4958: 0 | G4958: 0 | H4958: 0 | I4958: 10046718641

Sheet DataIO2021x58
A1: INPUT - OUTPUT TABLE OF THAILAND 2021 (58 Sectors)
A2: ROW | B2: Row label | C2: COLUMN | D2: Column label | E2: PURCHASER | F2: WHOLESALE | G2: RETAIL | H2: TRANSPORT | I2: IMPORT | R2: 1 | S2: Paddy
A3: 001 | B3: =vlookup(A3,R:S,2,0) | C3: 001 | E3: 23826912 | F3: 0 | G3: 0 | H3: 119524 | I3: 5 | R3: 2 | S3: Maize
A4: 002 | C4: 001 | E4: 0 | F4: 0 | G4: 0 | H4: 0 | I4: 0 | R4: 3 | S4: Cassava
A5: 003 | C5: 001 | E5: 0 | F5: 0 | G5: 0 | H5: 0 | I5: 0 | R5: 4 | S5: Beans and Nuts
A6: 004 | C6: 001 | E6: 0 | F6: 0 | G6: 0 | H6: 0 | I6: 0 | R6: 5 | S6: Vegetables and Fruits
A7: 005 | C7: 001 | E7: 0 | F7: 0 | G7: 0 | H7: 0 | I7: 0 | R7: 6 | S7: Sugarcane
A8: 006 | C8: 001 | E8: 0 | F8: 0 | G8: 0 | H8: 0 | I8: 0 | R8: 7 | S8: Rubber (Latex)
A9: 007 | C9: 001 | E9: 0 | F9: 0 | G9: 0 | H9: 0 | I9: 0 | R9: 8 | S9: Other Crops
A10: 008 | C10: 001 | E10: 16110576 | F10: 0 | G10: 0 | H10: 0 | I10: 0 | R10: 9 | S10: Livestock
A11: 009 | C11: 001 | E11: 0 | F11: 0 | G11: 0 | H11: 0 | I11: 0 | R11: 10 | S11: Forestry
A12: 010 | C12: 001 | E12: 4505 | F12: 19 | G12: 63 | H12: 97 | I12: 0 | R12: 11 | S12: Fishery
A13: 011 | C13: 001 | E13: 0 | F13: 0 | G13: 0 | H13: 0 | I13: 0 | R13: 12 | S13: Crude Oil and Coal
A14: 012 | C14: 001 | E14: 0 | F14: 0 | G14: 0 | H14: 0 | I14: 0 | R14: 13 | S14: Metal Ore
A15: 013 | C15: 001 | E15: 0 | F15: 0 | G15: 0 | H15: 0 | I15: 0 | R15: 14 | S15: Non-Metal Ore
... A85: 018 | C85: 002 | E85: 0 | F85: 0 | G85: 0 | H85: 0 | I85: 0 | R85: 700 | S85: Total Supply
A86: 019 | C86: 002 | E86: 0 | F86: 0 | G86: 0 | H86: 0 | I86: 0
A87: 020 | C87: 002 | E87: 0 | F87: 0 | G87: 0 | H87: 0 | I87: 0
A88: 021 | C88: 002 | E88: 0 | F88: 0 | G88: 0 | H88: 0 | I88: 0
A89: 022 | C89: 002 | E89: 0 | F89: 0 | G89: 0 | H89: 0 | I89: 0
A90: 023 | C90: 002 | E90: 0 | F90: 0 | G90: 0 | H90: 0 | I90: 0
A91: 024 | C91: 002 | E91: 208864 | F91: 40304 | G91: 4800 | H91: 1843 | I91: 0
A92: 025 | C92: 002 | E92: 554 | F92: 22 | G92: 16 | H92: 5 | I92: 0
A93: 026 | C93: 002 | E93: 0 | F93: 0 | G93: 0 | H93: 0 | I93: 0
A94: 027 | C94: 002 | E94: 0 | F94: 0 | G94: 0 | H94: 0 | I94: 0
A95: 028 | C95: 002 | E95: 6761322 | F95: 768586 | G95: 727783 | H95: 290677 | I95: 3881156
A96: 029 | C96: 002 | E96: 0 | F96: 0 | G96: 0 | H96: 0 | I96: 0
A97: 030 | C97: 002 | E97: 873484 | F97: 67102 | G97: 89490 | H97: 8932 | I97: 155366
... A4958: 190 | C4958: 700 | E4958: 46348019845 | F4958: 0 | G4958: 0 | H4958: 0 | I4958: 10046718641
