Workbook

Sheet DataIO2021
A1: INPUT - OUTPUT TABLE OF THAILAND 2021
A2: ROW | B2: ROW description | C2: COLUMN | D2: COLUMN description | E2: PURCHASER | F2: WHOLESALE | G2: RETAIL | H2: TRANSPORT | I2: IMPORT
A3: 001 | B3: =VLOOKUP(A3,'sector mapping'!A:B,2,0) | C3: 001 | D3: =VLOOKUP(C3,'sector mapping'!A:B,2,0) | E3: 23826912 | F3: 0 | G3: 0 | H3: 119524 | I3: 5
A4: 024 | B4: =VLOOKUP(A4,'sector mapping'!A:B,2,0) | C4: 001 | D4: =VLOOKUP(C4,'sector mapping'!A:B,2,0) | E4: 16110576 | F4: 0 | G4: 0 | H4: 0 | I4: 0
A5: 027 | B5: =VLOOKUP(A5,'sector mapping'!A:B,2,0) | C5: 001 | D5: =VLOOKUP(C5,'sector mapping'!A:B,2,0) | E5: 4505 | F5: 19 | G5: 63 | H5: 97 | I5: 0
A6: 071 | B6: =VLOOKUP(A6,'sector mapping'!A:B,2,0) | C6: 001 | D6: =VLOOKUP(C6,'sector mapping'!A:B,2,0) | E6: 728 | F6: 12 | G6: 0 | H6: 6 | I6: 0
A7: 074 | B7: =VLOOKUP(A7,'sector mapping'!A:B,2,0) | C7: 001 | D7: =VLOOKUP(C7,'sector mapping'!A:B,2,0) | E7: 29446 | F7: 3256 | G7: 507 | H7: 178 | I7: 0
A8: 078 | B8: =VLOOKUP(A8,'sector mapping'!A:B,2,0) | C8: 001 | D8: =VLOOKUP(C8,'sector mapping'!A:B,2,0) | E8: 5485 | F8: 684 | G8: 1020 | H8: 65 | I8: 0
A9: 085 | B9: =VLOOKUP(A9,'sector mapping'!A:B,2,0) | C9: 001 | D9: =VLOOKUP(C9,'sector mapping'!A:B,2,0) | E9: 43078118 | F9: 3655127 | G9: 2729612 | H9: 1325438 | I9: 24777541
A10: 088 | B10: =VLOOKUP(A10,'sector mapping'!A:B,2,0) | C10: 001 | D10: =VLOOKUP(C10,'sector mapping'!A:B,2,0) | E10: 32700 | F10: 2839 | G10: 3913 | H10: 208 | I10: 0
A11: 093 | B11: =VLOOKUP(A11,'sector mapping'!A:B,2,0) | C11: 001 | D11: =VLOOKUP(C11,'sector mapping'!A:B,2,0) | E11: 9834163 | F11: 376017 | G11: 350703 | H11: 88441 | I11: 1964873
A12: 094 | B12: =VLOOKUP(A12,'sector mapping'!A:B,2,0) | C12: 001 | D12: =VLOOKUP(C12,'sector mapping'!A:B,2,0) | E12: 256626 | F12: 24729 | G12: 12855 | H12: 4387 | I12: 0
A13: 097 | B13: =VLOOKUP(A13,'sector mapping'!A:B,2,0) | C13: 001 | D13: =VLOOKUP(C13,'sector mapping'!A:B,2,0) | E13: 8953 | F13: 1698 | G13: 1304 | H13: 236 | I13: 0
A14: 098 | B14: =VLOOKUP(A14,'sector mapping'!A:B,2,0) | C14: 001 | D14: =VLOOKUP(C14,'sector mapping'!A:B,2,0) | E14: 423548 | F14: 9127 | G14: 23654 | H14: 3032 | I14: 104099
... A12713: 190 | B12713: =VLOOKUP(A12713,'sector mapping'!A:B,2,0) | C12713: 700 | D12713: =VLOOKUP(C12713,'sector mapping'!A:B,2,0) | E12713: 46348019845 | F12713: 0 | G12713: 0 | H12713: 0 | I12713: 10046718641

Sheet sector mapping
A1: code | B1: IO sector | C1: Industry of the future
A2: 001 | B2: Paddy | C2: Agribusiness
A3: 002 | B3: Maize | C3: Agribusiness
A4: 003 | B4: Other cereals | C4: Agribusiness
A5: 004 | B5: Cassava | C5: Agribusiness
A6: 005 | B6: Other root crops | C6: Agribusiness
A7: 006 | B7: Beans and nuts | C7: Agribusiness
A8: 007 | B8: Vegetable | C8: Agribusiness
A9: 008 | B9: Fruits | C9: Agribusiness
A10: 009 | B10: Sugar cane | C10: Agribusiness
A11: 010 | B11: Coconut | C11: Agribusiness
A12: 011 | B12: Oil palm | C12: Agribusiness
... A30: 029 | B30: Inland fishing | C30: Agribusiness
A31: 030 | B31: Coal and lignite
A32: 031 | B32: Petroleum and natural gas
A33: 032 | B33: Iron ore
A34: 033 | B34: Tin ore
A35: 034 | B35: Tungsten ore
A36: 035 | B36: Other non-ferrous metals
A37: 036 | B37: Fluorite
A38: 037 | B38: Chemical fertilizers
A39: 038 | B39: Salt
A40: 039 | B40: Limestone
A41: 040 | B41: Stone quarrying
A42: 041 | B42: Other mining and quarrying
A43: 042 | B43: Slaughtering | C43: Agribusiness
A44: 043 | B44: Canning and preserving of meat | C44: Agribusiness
A45: 044 | B45: Dairy products | C45: Agribusiness
A46: 045 | B46: Canning and preservation of fruit and vegetables | C46: Agribusiness
A47: 046 | B47: Canning and preservation of fish and other sea foods | C47: Agribusiness
A48: 047 | B48: Coconut and palm oil | C48: Agribusiness
A49: 048 | B49: Animal oil, animal fat, vegetable oil and by-products | C49: Agribusiness
A50: 049 | B50: Rice milling | C50: Agribusiness
A51: 050 | B51: Tapioca milling | C51: Agribusiness
A52: 051 | B52: Grinding of maize | C52: Agribusiness
A53: 052 | B53: Flour and other grain milling | C53: Agribusiness
A54: 053 | B54: Bakery products | C54: Agribusiness
... A67: 066 | B67: Tobacco products | C67: Agribusiness
A68: 067 | B68: Spinning
A69: 068 | B69: Weaving
A70: 069 | B70: Textile bleaching, printing and finishing
A71: 070 | B71: Made-up textile goods
A72: 071 | B72: Knitting
A73: 072 | B73: Wearing apparel
A74: 073 | B74: Carpets and rugs
A75: 074 | B75: Jute mill products
A76: 075 | B76: Tanneries and leather finishing
A77: 076 | B77: Leather products
A78: 077 | B78: Footwear, except of rubber
A79: 078 | B79: Saw mills
... A83: 082 | B83: Paper and paperboard products
A84: 083 | B84: Printing and publishing | C84: Creative industries
A85: 084 | B85: Basic industrial chemicals | C85: Advanced manufacturing
A86: 085 | B86: Fertilizer and pesticides | C86: Agribusiness
A87: 086 | B87: Petrochemical products
A88: 087 | B88: Paints
A89: 088 | B89: Drugs and medicines | C89: Advanced manufacturing
A90: 089 | B90: Soap and cleaning preparations
A91: 090 | B91: Cosmetic
A92: 091 | B92: Matches
A93: 092 | B93: Other chemical products | C93: Advanced manufacturing
A94: 093 | B94: Petroleum refineries
A95: 094 | B95: Other petroleum products
A96: 095 | B96: Rubber sheet and block rubber
A97: 096 | B97: Tyres and tubes
A98: 097 | B98: Other rubber products
A99: 098 | B99: Plastic ware
A100: 099 | B100: Ceramic and earthen ware
A101: 100 | B101: Glass and glass products
A102: 101 | B102: Structural clay products
A103: 102 | B103: Cement
A104: 103 | B104: Concrete and cement products
A105: 104 | B105: Other non-metallic products
... A112: 111 | B112: Other fabricated metal products
A113: 112 | B113: Engines and turbines | C113: Advanced manufacturing
A114: 113 | B114: Agricultural machinery and equipment | C114: Advanced manufacturing
A115: 114 | B115: Wood and metal working machines | C115: Advanced manufacturing
A116: 115 | B116: Special industrial machinery | C116: Advanced manufacturing
A117: 116 | B117: Office and household machinery and appliances | C117: Advanced manufacturing
A118: 117 | B118: Electrical industrial machinery and appliances | C118: Advanced manufacturing
A119: 118 | B119: Radio, television and communication equipment and apparatus | C119: Advanced manufacturing
A120: 119 | B120: Household electrical appliances | C120: Advanced manufacturing
A121: 120 | B121: Insulated wire and cable
A122: 121 | B122: Electric accumulators and batteries | C122: Advanced manufacturing
A123: 122 | B123: Other electrical apparatus and supplies | C123: Advanced manufacturing
A124: 123 | B124: Ship building and repairing | C124: Advanced manufacturing
A125: 124 | B125: Railroad equipment | C125: Advanced manufacturing
A126: 125 | B126: Motor vehicles | C126: Advanced manufacturing
A127: 126 | B127: Motorcycles | C127: Advanced manufacturing
A128: 127 | B128: Repair of motor vehicles
A129: 128 | B129: Aircraft | C129: Advanced manufacturing
A130: 129 | B130: Scientific equipment | C130: Advanced manufacturing
A131: 130 | B131: Photographic and optical goods | C131: Advanced manufacturing
A132: 131 | B132: Watches and clocks
A133: 132 | B133: Jewellery and related articles | C133: Creative industries
A134: 133 | B134: Recreational and athletic equipment
A135: 134 | B135: Other manufactured goods
A136: 135 | B136: Electricity
A137: 136 | B137: Pipe line and gas distribution
A138: 137 | B138: Water work and supply
...
